Workbook

Sheet Run
A1: run_label | B1: testId | C1: passed | D1: hallucination | E1: route | F1: model | G1: latencyMs | H1: promptTokens | I1: completionTokens | J1: traceId | K1: output | L1: fullOutput | M1: riskRelevanceScore | N1: riskRelevancePass | O1: riskRelevanceReason | P1: unsupportedItems | Q1: judgeModel | R1: judgeTokens
A2: Run 2 - gpt-4o-mini - after Orchestrator fix | B2: T1 | C2: TRUE | D2: FALSE | E2: plan | F2: gpt-4o-mini-2024-07-18 | G2: 6187 | H2: 918 | I2: 603 | J2: 185b2e70b3ecfcb2300ce71874d9e979 | K2: # AI Adoption Project Plan for ABCDE Ltd. ## Project Summary ABCDE Ltd., a mid-sized enterprise specializing in logistics and supply chain solutions, is initiating an AI adoption project aimed at enhancing operational efficiency, improving customer experience, and driving data-driven decision-makin
A3: Run 2 - gpt-4o-mini - after Orchestrator fix | B3: T2 | C3: TRUE | D3: FALSE | E3: clarify | J3: 346663edcd53057dd38af84708c5dd79 | K3: This request does not have enough detail. To build a plan I need: the project scope, the goals, the deliverables, the timeline and the team size.
A4: Run 2 - gpt-4o-mini - after Orchestrator fix | B4: T3 | C4: TRUE | D4: FALSE | E4: risk | F4: gpt-4o-mini-2024-07-18 | G4: 5743 | H4: 1434 | I4: 617 | J4: 5b43e1fc1846f8fff262ab89bd07322b | K4: | Risk ID | Category | Risk Challenge | Impact | Mitigation Strategy | |---------|--------------------------------|-------------------------------------------------|--
A5: Run 2 - gpt-4o-mini - after Orchestrator fix | B5: T4 | C5: TRUE | D5: FALSE | E5: clarify | J5: 8b24e61e5b44d5a3998b996c671fd4b4 | K5: This request does not have enough detail. To assess risks I need: the project description or scope, the timeline, the domain or technology, and the team or stakeholders.
A6: Run 2 - gpt-4o-mini - after Orchestrator fix | B6: T5 | C6: TRUE | D6: FALSE | E6: status | F6: gpt-4o-mini-2024-07-18 | G6: 2692 | H6: 812 | I6: 243 | J6: 178b20128f944acd14342b3d77e4ff7b | K6: **Weekly Status Report** **As-of Date:** 2026-04-20 **Overall Health:** Amber - There are two tasks marked as "To Do," and one task is flagged "At risk." **Counts by Status:** Done: 0 In Progress: 2 To Do: 2 Blocked: 0 Total: 4 **Tasks Grouped by Status:** **In Progress:** - T
A7: Run 2 - gpt-4o-mini - after Orchestrator fix | B7: T6 | C7: TRUE | D7: FALSE | E7: clarify | J7: b9a0006b6aaf4cbb6061fa5be62d22cc | K7: This request does not have enough detail. No task data is available for this request, so I cannot report status. Please share the task board export (CSV) or a task list with statuses.
A8: Run 2 - gpt-4o-mini - after Orchestrator fix | B8: T7 | C8: TRUE | D8: FALSE | E8: risk | F8: gpt-4o-mini-2024-07-18 | G8: 2578 | H8: 1433 | I8: 215 | J8: b48025351e84030869d44e14422426a5 | K8: 1. **Risk ID:** R06 **Category:** Cost Overruns **Impact:** Budget constraints and project delays **Mitigation:** Set realistic budget and build in contingency funds **Reason:** The task T010 (Collect historical demand data) is still to do, which may lead to underestimating AI de
A9: Run 2 - gpt-4o-mini - after Orchestrator fix | B9: T8 | C9: TRUE | D9: FALSE | E9: milestones | F9: gpt-4o-mini-2024-07-18 | G9: 2238 | H9: 1057 | I9: 193 | J9: 839c9cb3fe335f54e90acfa76a5b3f5c | K9: Here are the flagged tasks that are blocked or at risk: 1. **Blocked Task** - **Task ID:** T024 - **Task Name:** Security review of AI infrastructure - **Status:** Blocked - **Due Date:** 2026-05-26 - **Flag:** Blocked - **Reason:** Waiting for security team availability - **Su
A10: Run 2 - gpt-4o-mini - after Orchestrator fix | B10: T9 | C10: TRUE | D10: FALSE | E10: clarify | J10: 64ca21fcf24746aced06f4a42305ec9a | K10: This request does not have enough detail. To build a plan I need: the project scope, the goals, the deliverables, the timeline and the team size.
A11: Run 2 - gpt-4o-mini - after Orchestrator fix | B11: T10 | C11: TRUE | D11: FALSE | E11: status | F11: gpt-4o-mini-2024-07-18 | G11: 1110 | H11: 2421 | I11: 37 | J11: 847f6366c535f85a3ffa221bda97f120 | K11: Done 5, In Progress 3, To Do 16, Blocked 1, Total 25. The Blocked task is T024: Security review of AI infrastructure. As-of date: 2026-04-20. Sources: project_description.txt, project_timeline.csv, project_risks.csv, sample_task_board.csv.
A12: Run 2 - gpt-4o-mini - after Orchestrator fix | B12: T11 | C12: TRUE | D12: FALSE | E12: milestones | F12: gpt-4o-mini-2024-07-18 | G12: 1378 | H12: 1056 | I12: 65 | J12: 5cf458b39a4a4b913bb0de4642759807 | K12: The upcoming milestones in the next 2 weeks are: 1. Current systems audit report - Due by 2026-04-21 2. Gap analysis report - Due by 2026-04-21 3. Final list of prioritized use cases with success criteria - Due by 2026-05-05 As-of date: 2026-04-20. Sources: project_description.txt, project_timelin
A13: Run 2 - gpt-4o-mini - after Orchestrator fix | B13: T12 | C13: TRUE | D13: FALSE | E13: status | F13: gpt-4o-mini-2024-07-18 | G13: 3069 | H13: 711 | I13: 238 | J13: b082ab04711a3dfdf71b5370686c3e1a | K13: Subject: Sprint 2 Progress Update - ABCDE Ltd. AI Adoption Project Dear Stakeholders, As of April 20, 2026, I am pleased to provide you with an update on the progress of Sprint 2 for the ABCDE Ltd. AI Adoption Project. **Progress by Task:** - **T004: Audit existing data infrastructure** - Status:
A14: Run 3 - gpt-4o-mini - T11 prompt fix | B14: T1 | C14: TRUE | D14: FALSE | E14: plan | F14: gpt-4o-mini-2024-07-18 | G14: 4926 | H14: 918 | I14: 606 | J14: 3d9b0efa2cd3b9cfbf5fdf4317a5e4e6 | K14: # AI Adoption Project Plan for ABCDE Ltd. ## Project Summary ABCDE Ltd., a mid-sized enterprise specializing in logistics and supply chain solutions, is initiating an AI adoption project aimed at enhancing operational efficiency, improving customer experience, and driving data-driven decision-makin | L14: # AI Adoption Project Plan for ABCDE Ltd. ## Project Summary ABCDE Ltd., a mid-sized enterprise specializing in logistics and supply chain solutions, is initiating an AI adoption project aimed at enhancing operational efficiency, improving customer experience, and driving data-driven decision-making. The project will integrate AI-powered tools into core business functions such as demand forecasting, route optimization, inventory management, and customer support. The initiative will be executed in phases, starting with an assessment of current workflows and data infrastructure, followed by pilot implementations in targeted departments. ## Goals - Reduce delivery delays by 15% - Lower operational costs by 10% - Improve service responsiveness ## Phases Table | Phase | Weeks | Key Activities | Milestones | End Date | |---------------------------|--------|---------------------------------------------------------|-----------------------------------------------------|-------------| | Project Initiation | 1-2 | Define project scope; Form cross-functional team; Initial stakeholder meeting | Project charter signed off; Team structure finalized | 2026-04-10 | | Current State Analysis | 3-4 | Assess existing processes & systems; Identify data sources & gaps | Current systems audit report; Gap analysis report | 2026-04-21 | | Use Case Selection | 5-6 | Shortlist priority AI use cases (forecasting, route optimization) | Final list of prioritized use cases with success criteria | 2026-05-05 | | Pilot Design | 7-10 | Data collection & preparation; Model design and development | Working prototype models; Data pipelines established | 2026-06-02 | | Pilot Implementation | 11-14 | Deploy AI models in test environments; Monitor performance | Pilot results report; User feedback and performance metrics | 2026-06-16 | | Evaluation & Iteration | 15-16 | Evaluate pilot outcomes; Adjust models as needed | Updated models and process refinements | 2026-06-30 | | Full Deployment | 17-22 | Scale AI models across selected departments; Train staff | Full production rollout; Training sessions completed | 2026-07-21 | | Monitoring & Review | 23-24 | Continuous performance monitoring; Final project review | Project closure report; Recommendations for future scaling | 2026-08-04 | ## Timeline Overview The project will span a total of 24 weeks, starting from April 10, 2026, and concluding on August 4, 2026. Each phase is designed to build upon the previous one, ensuring a structured approach to AI adoption. ## Assumptions and Gaps - Proposed, not in source: Specific team sizes and roles for the cross-functional task force. - Proposed, not in source: Detailed budget allocation for each phase of the project. ## Sources - Project description provided by ABCDE Ltd. As-of date: 2026-04-20. Sources: project_description.txt, project_timeline.csv, project_risks.csv, sample_task_board.csv.
A15: Run 3 - gpt-4o-mini - T11 prompt fix | B15: T2 | C15: TRUE | D15: FALSE | E15: clarify | J15: d4dbdb6a3e4b4d05bc4562dc438fe93a | K15: This request does not have enough detail. To build a plan I need: the project scope, the goals, the deliverables, the timeline and the team size. | L15: This request does not have enough detail. To build a plan I need: the project scope, the goals, the deliverables, the timeline and the team size.
A16: Run 3 - gpt-4o-mini - T11 prompt fix | B16: T3 | C16: TRUE | D16: FALSE | E16: risk | F16: gpt-4o-mini-2024-07-18 | G16: 5068 | H16: 1434 | I16: 604 | J16: 7a48c39a830e2af448bff2f204345583 | K16: | Risk ID | Category | Risk Challenge | Impact | Mitigation Strategy | |---------|--------------------------------|-------------------------------------------------|-- | L16: | Risk ID | Category | Risk Challenge | Impact | Mitigation Strategy | |---------|--------------------------------|-------------------------------------------------|------------------------------------------------|---------------------------------------------------------| | R01 | Data Quality & Availability | Incomplete or unstructured data | Poor model performance and inaccurate outcomes | Perform early data audits and implement robust data governance | | R02 | Integration Issues | Difficulty integrating AI with legacy systems | Delays in deployment and operational disruptions | Plan integration roadmap and use APIs/middleware | | R03 | Talent & Skills Gap | Lack of internal AI/ML expertise | Overreliance on external vendors and slow progress | Provide staff training and hire specialized talent | | R04 | Change Resistance | Employees resist adopting AI-driven workflows | Low adoption and reduced ROI | Strong change management and early engagement | | R05 | Ethical & Legal Concerns | Risks of biased models or data privacy violations | Legal repercussions and reputational damage | Involve legal early and implement fairness checks | | R06 | Cost Overruns | Underestimation of AI development costs | Budget constraints and project delays | Set realistic budget and build in contingency funds | | R07 | Unrealistic Expectations | Stakeholders expect immediate ROI | Disillusionment and loss of support | Align expectations and show quick wins | | R08 | Model Performance Drift | AI models lose accuracy over time | Incorrect decisions and trust erosion | Regular retraining cycles and monitoring dashboards | | R09 | Security Vulnerabilities | AI models targeted by adversarial attacks | Data breaches and operational risks | Adopt AI security best practices and penetration testing | | R10 | Vendor Lock-in | Overdependence on a specific AI platform | Flexibility loss and future switching costs | Favor open standards and negotiate flexible vendor terms | ### Top Risks and Why 1. **R06 - Cost Overruns**: The task "Vendor evaluation for ML platform" (T009) is still to do, which may lead to underestimating costs. 2. **R03 - Talent & Skills Gap**: The task "Staff training program" (T020) is still to do, indicating a lack of internal expertise. 3. **R01 - Data Quality & Availability**: The task "Identify data gaps and quality issues" (T006) is in progress, highlighting potential data challenges. 4. **R05 - Ethical & Legal Concerns**: The task "Legal review of data usage" (T025) is in progress, which may expose legal risks. 5. **R04 - Change Resistance**: The task "Staff training program" (T020) is still to do, which may lead to resistance in adopting AI workflows. ### Sources - Risks and mitigation strategies were derived from the provided risk list. - Task statuses were referenced from the provided task list. As-of date: 2026-04-20. Sources: project_description.txt, project_timeline.csv, project_risks.csv, sample_task_board.csv.
A17: Run 3 - gpt-4o-mini - T11 prompt fix | B17: T4 | C17: TRUE | D17: FALSE | E17: clarify | J17: cbb74a04f390117f352c6a2b54436c26 | K17: This request does not have enough detail. To assess risks I need: the project description or scope, the timeline, the domain or technology, and the team or stakeholders. | L17: This request does not have enough detail. To assess risks I need: the project description or scope, the timeline, the domain or technology, and the team or stakeholders.
A18: Run 3 - gpt-4o-mini - T11 prompt fix | B18: T5 | C18: TRUE | D18: FALSE | E18: status | F18: gpt-4o-mini-2024-07-18 | G18: 2990 | H18: 812 | I18: 246 | J18: 63913ba29f138820e589d9c1aa1dd3e8 | K18: **Weekly Status Report** **As-of Date:** 2026-04-20 **Overall Health:** Amber - There are two tasks marked as "To Do," and one task is flagged "At risk." **Counts by Status:** - Done: 0 - In Progress: 2 - To Do: 2 - Blocked: 0 - Total: 4 **Tasks Grouped by Status:** **In Progres | L18: **Weekly Status Report** **As-of Date:** 2026-04-20 **Overall Health:** Amber - There are two tasks marked as "To Do," and one task is flagged "At risk." **Counts by Status:** - Done: 0 - In Progress: 2 - To Do: 2 - Blocked: 0 - Total: 4 **Tasks Grouped by Status:** **In Progress:** - T007: Shortlist AI use cases - T025: Legal review of data usage **To Do:** - T008: Define success criteria for each use case - T009: Vendor evaluation for ML platform **Blocked Items:** - None **Upcoming Milestones:** - Current State Analysis (Due: 2026-04-21) - Activities: Assess existing processes & systems; Identify data sources & gaps - Milestones: Current systems audit report; Gap analysis report **Risks or Actions Needed:** - T008: Define success criteria for each use case is flagged "At risk" and needs attention to ensure timely completion. --- This concludes the weekly status report. As-of date: 2026-04-20. Sources: project_description.txt, project_timeline.csv, project_risks.csv, sample_task_board.csv.
A19: Run 3 - gpt-4o-mini - T11 prompt fix | B19: T6 | C19: TRUE | D19: FALSE | E19: clarify | J19: ed7cbc8638e475422f732e8e709e0d6a | K19: This request does not have enough detail. No task data is available for this request, so I cannot report status. Please share the task board export (CSV) or a task list with statuses. | L19: This request does not have enough detail. No task data is available for this request, so I cannot report status. Please share the task board export (CSV) or a task list with statuses.
A20: Run 3 - gpt-4o-mini - T11 prompt fix | B20: T7 | C20: TRUE | D20: FALSE | E20: risk | F20: gpt-4o-mini-2024-07-18 | G20: 2640 | H20: 1433 | I20: 213 | J20: b4120701d48f0c4a1189ed45b360b890 | K20: 1. **Risk ID:** R06 **Category:** Cost Overruns **Impact:** Budget constraints and project delays **Mitigation:** Set realistic budget and build in contingency funds **Reason:** The task T010 (Collect historical demand data) is still to do, which may lead to underestimating AI de | L20: 1. **Risk ID:** R06 **Category:** Cost Overruns **Impact:** Budget constraints and project delays **Mitigation:** Set realistic budget and build in contingency funds **Reason:** The task T010 (Collect historical demand data) is still to do, which may lead to underestimating AI development costs. 2. **Risk ID:** R01 **Category:** Data Quality & Availability **Impact:** Poor model performance and inaccurate outcomes **Mitigation:** Perform early data audits and implement robust data governance **Reason:** The task T006 (Identify data gaps and quality issues) is in progress, highlighting potential data quality challenges. 3. **Risk ID:** R05 **Category:** Ethical & Legal Concerns **Impact:** Legal repercussions and reputational damage **Mitigation:** Involve legal early and implement fairness checks **Reason:** The task T025 (Legal review of data usage) is in progress, indicating ongoing concerns about data ethics and compliance. As-of date: 2026-04-20. Sources: project_description.txt, project_timeline.csv, project_risks.csv, sample_task_board.csv.
A21: Run 3 - gpt-4o-mini - T11 prompt fix | B21: T8 | C21: TRUE | D21: FALSE | E21: milestones | F21: gpt-4o-mini-2024-07-18 | G21: 1993 | H21: 1113 | I21: 180 | J21: eabb14b15a66e3920829d37f0e0ff7c5 | K21: 1. **Blocked Tasks:** - **Task ID:** T024 - **Name:** Security review of AI infrastructure - **Status:** Blocked - **Due Date:** 2026-05-26 - **Flag:** Blocked - **Reason:** waiting for security team availability - **Suggested Action:** Follow up with the security te | L21: 1. **Blocked Tasks:** - **Task ID:** T024 - **Name:** Security review of AI infrastructure - **Status:** Blocked - **Due Date:** 2026-05-26 - **Flag:** Blocked - **Reason:** waiting for security team availability - **Suggested Action:** Follow up with the security team to confirm availability and expedite the review process. 2. **At Risk Tasks:** - **Task ID:** T008 - **Name:** Define success criteria for each use case - **Status:** To Do - **Due Date:** 2026-05-02 - **Flag:** At risk - **Reason:** 12 days to due - **Suggested Action:** Prioritize this task to ensure success criteria are defined before the deadline. As-of date: 2026-04-20. Sources: project_description.txt, project_timeline.csv, project_risks.csv, sample_task_board.csv.
A22: Run 3 - gpt-4o-mini - T11 prompt fix | B22: T9 | C22: TRUE | D22: FALSE | E22: clarify | J22: f86ea517d9c39c0adbb799fed07c101c | K22: This request does not have enough detail. To build a plan I need: the project scope, the goals, the deliverables, the timeline and the team size. | L22: This request does not have enough detail. To build a plan I need: the project scope, the goals, the deliverables, the timeline and the team size.
A23: Run 3 - gpt-4o-mini - T11 prompt fix | B23: T10 | C23: TRUE | D23: FALSE | E23: status | F23: gpt-4o-mini-2024-07-18 | G23: 992 | H23: 2421 | I23: 35 | J23: 6168039fbf07ec8e5d35d76534699320 | K23: Done 5, In Progress 3, To Do 16, Blocked 1, Total 25. Blocked task: T024 Security review of AI infrastructure. As-of date: 2026-04-20. Sources: project_description.txt, project_timeline.csv, project_risks.csv, sample_task_board.csv. | L23: Done 5, In Progress 3, To Do 16, Blocked 1, Total 25. Blocked task: T024 Security review of AI infrastructure. As-of date: 2026-04-20. Sources: project_description.txt, project_timeline.csv, project_risks.csv, sample_task_board.csv.
A24: Run 3 - gpt-4o-mini - T11 prompt fix | B24: T11 | C24: TRUE | D24: FALSE | E24: milestones | F24: gpt-4o-mini-2024-07-18 | G24: 1388 | H24: 1112 | I24: 47 | J24: 900a4b569255b8bfdbec527d6fb9cf8c | K24: Milestones in the next 2 weeks: 1. Current systems audit report 2. Gap analysis report Next milestone after this window: Final list of prioritized use cases with success criteria (due 2026-05-05). As-of date: 2026-04-20. Sources: project_description.txt, project_timeline.csv, project_risks.csv, sa | L24: Milestones in the next 2 weeks: 1. Current systems audit report 2. Gap analysis report Next milestone after this window: Final list of prioritized use cases with success criteria (due 2026-05-05). As-of date: 2026-04-20. Sources: project_description.txt, project_timeline.csv, project_risks.csv, sample_task_board.csv.
A25: Run 3 - gpt-4o-mini - T11 prompt fix | B25: T12 | C25: TRUE | D25: FALSE | E25: status | F25: gpt-4o-mini-2024-07-18 | G25: 3110 | H25: 711 | I25: 249 | J25: bda81c6e4250ae22b7749860e7e605fc | K25: Subject: Sprint 2 Progress Update - ABCDE Ltd. AI Adoption Project Dear Stakeholders, As of April 20, 2026, I am pleased to provide you with an update on the progress of Sprint 2 for the ABCDE Ltd. AI Adoption Project. **Progress Overview:** - **Task T004: Audit existing data infrastructure** - S | L25: Subject: Sprint 2 Progress Update - ABCDE Ltd. AI Adoption Project Dear Stakeholders, As of April 20, 2026, I am pleased to provide you with an update on the progress of Sprint 2 for the ABCDE Ltd. AI Adoption Project. **Progress Overview:** - **Task T004: Audit existing data infrastructure** - Status: Done (Assignee: Priya Nair) - **Task T005: Map current logistics workflows** - Status: Done (Assignee: James Wong) - **Task T006: Identify data gaps and quality issues** - Status: In Progress (Assignee: Priya Nair) **Next Steps for Open Tasks:** - For **Task T006: Identify data gaps and quality issues**, Priya Nair is currently working on the gap analysis report, which is due on April 21, 2026. This task is flagged for monitoring as it is still in progress. Overall, we have completed 2 tasks and have 1 task currently in progress. The project is on track, with no blocked items at this time. Thank you for your continued support. Best regards, Mira Project Assistant Nexora Pvt. Ltd. As-of date: 2026-04-20. Sources: project_description.txt, project_timeline.csv, project_risks.csv, sample_task_board.csv.
A26: Run 4 - gpt-4o-mini - with risk judge | B26: T1 | C26: TRUE | D26: FALSE | E26: plan | F26: gpt-4o-mini-2024-07-18 | G26: 5407 | H26: 918 | I26: 613 | J26: 5be90b6b5694f430699a5d664f61fda2 | K26: # AI Adoption Project Plan for ABCDE Ltd. ## Project Summary ABCDE Ltd., a mid-sized enterprise specializing in logistics and supply chain solutions, is initiating an AI adoption project aimed at enhancing operational efficiency, improving customer experience, and driving data-driven decision-makin | L26: # AI Adoption Project Plan for ABCDE Ltd. ## Project Summary ABCDE Ltd., a mid-sized enterprise specializing in logistics and supply chain solutions, is initiating an AI adoption project aimed at enhancing operational efficiency, improving customer experience, and driving data-driven decision-making. The project will integrate AI-powered tools into core business functions such as demand forecasting, route optimization, inventory management, and customer support. The initiative will be executed in phases, starting with an assessment of current workflows and data infrastructure, followed by pilot implementations in targeted departments. ## Goals - Reduce delivery delays by 15% - Lower operational costs by 10% - Improve service responsiveness ## Phases Table | Phase | Weeks | Key Activities | Milestones | End Date | |---------------------------|---------|---------------------------------------------------------|-----------------------------------------------------|--------------| | Project Initiation | 1-2 | Define project scope; Form cross-functional team; Initial stakeholder meeting | Project charter signed off; Team structure finalized | 2026-04-10 | | Current State Analysis | 3-4 | Assess existing processes & systems; Identify data sources & gaps | Current systems audit report; Gap analysis report | 2026-04-21 | | Use Case Selection | 5-6 | Shortlist priority AI use cases (forecasting, route optimization) | Final list of prioritized use cases with success criteria | 2026-05-05 | | Pilot Design | 7-10 | Data collection & preparation; Model design and development | Working prototype models; Data pipelines established | 2026-06-02 | | Pilot Implementation | 11-14 | Deploy AI models in test environments; Monitor performance | Pilot results report; User feedback and performance metrics | 2026-06-16 | | Evaluation & Iteration | 15-16 | Evaluate pilot outcomes; Adjust models as needed | Updated models and process refinements | 2026-06-30 | | Full Deployment | 17-22 | Scale AI models across selected departments; Train staff | Full production rollout; Training sessions completed | 2026-07-21 | | Monitoring & Review | 23-24 | Continuous performance monitoring; Final project review | Project closure report; Recommendations for future scaling | 2026-08-04 | ## Timeline Overview The project will span a total of 24 weeks, starting from the initiation phase and concluding with the monitoring and review phase. Each phase is designed to build upon the previous one, ensuring a structured approach to AI adoption. ## Assumptions and Gaps - Proposed, not in source: Specific team sizes and roles for the cross-functional team. - Proposed, not in source: Detailed budget for the project phases. - Proposed, not in source: Specific tools and technologies to be used for AI implementation. ## Sources - Project description provided by ABCDE Ltd. As-of date: 2026-04-20. Sources: project_description.txt, project_timeline.csv, project_risks.csv, sample_task_board.csv. | M26: n/a | N26: n/a
A27: Run 4 - gpt-4o-mini - with risk judge | B27: T2 | C27: TRUE | D27: FALSE | E27: clarify | J27: 838d10895fd5cf257871db62df4758aa | K27: This request does not have enough detail. To build a plan I need: the project scope, the goals, the deliverables, the timeline and the team size. | L27: This request does not have enough detail. To build a plan I need: the project scope, the goals, the deliverables, the timeline and the team size. | M27: n/a | N27: n/a
A28: Run 4 - gpt-4o-mini - with risk judge | B28: T3 | C28: TRUE | D28: FALSE | E28: risk | F28: gpt-4o-mini-2024-07-18 | G28: 5435 | H28: 1434 | I28: 548 | J28: c2909017633e196947f03c1823b835c3 | K28: | Risk ID | Category | Risk Challenge | Impact | Mitigation Strategy | |---------|--------------------------------|-------------------------------------------------|-- | L28: | Risk ID | Category | Risk Challenge | Impact | Mitigation Strategy | |---------|--------------------------------|-------------------------------------------------|------------------------------------------------|---------------------------------------------------------| | R01 | Data Quality & Availability | Incomplete or unstructured data | Poor model performance and inaccurate outcomes | Perform early data audits and implement robust data governance | | R02 | Integration Issues | Difficulty integrating AI with legacy systems | Delays in deployment and operational disruptions | Plan integration roadmap and use APIs/middleware | | R03 | Talent & Skills Gap | Lack of internal AI/ML expertise | Overreliance on external vendors and slow progress | Provide staff training and hire specialized talent | | R04 | Change Resistance | Employees resist adopting AI-driven workflows | Low adoption and reduced ROI | Strong change management and early engagement | | R05 | Ethical & Legal Concerns | Risks of biased models or data privacy violations | Legal repercussions and reputational damage | Involve legal early and implement fairness checks | | R06 | Cost Overruns | Underestimation of AI development costs | Budget constraints and project delays | Set realistic budget and build in contingency funds | | R07 | Unrealistic Expectations | Stakeholders expect immediate ROI | Disillusionment and loss of support | Align expectations and show quick wins | | R08 | Model Performance Drift | AI models lose accuracy over time | Incorrect decisions and trust erosion | Regular retraining cycles and monitoring dashboards | | R09 | Security Vulnerabilities | AI models targeted by adversarial attacks | Data breaches and operational risks | Adopt AI security best practices and penetration testing | | R10 | Vendor Lock-in | Overdependence on a specific AI platform | Flexibility loss and future switching costs | Favor open standards and negotiate flexible vendor terms | ### Top Risks and Why 1. **R06 - Cost Overruns**: The task of setting a realistic budget and building in contingency funds is crucial, especially as the project progresses and costs may be underestimated (T024 - Security review of AI infrastructure is blocked). 2. **R05 - Ethical & Legal Concerns**: The ongoing legal review of data usage (T025) highlights the importance of addressing potential legal repercussions and reputational damage. 3. **R01 - Data Quality & Availability**: The task of identifying data gaps and quality issues (T006) is currently in progress, which directly relates to the risk of incomplete or unstructured data affecting model performance. ### Sources - Risks and mitigation strategies provided in the input. - Project tasks and their statuses. As-of date: 2026-04-20. Sources: project_description.txt, project_timeline.csv, project_risks.csv, sample_task_board.csv. | M28: 5 | N28: TRUE | O28: All risks and mitigations listed in Mira's answer are directly from the reference risk register and are highly relevant to the AI Adoption Project at ABCDE Ltd. | Q28: gpt-4o-mini-2024-07-18 | R28: 1281
A29: Run 4 - gpt-4o-mini - with risk judge | B29: T4 | C29: TRUE | D29: FALSE | E29: clarify | J29: b988f2615f41091bca05ca85ef9932bc | K29: This request does not have enough detail. To assess risks I need: the project description or scope, the timeline, the domain or technology, and the team or stakeholders. | L29: This request does not have enough detail. To assess risks I need: the project description or scope, the timeline, the domain or technology, and the team or stakeholders. | M29: n/a | N29: n/a
A30: Run 4 - gpt-4o-mini - with risk judge | B30: T5 | C30: TRUE | D30: FALSE | E30: status | F30: gpt-4o-mini-2024-07-18 | G30: 2453 | H30: 812 | I30: 241 | J30: 9ab909fd0fefd273c49ad7ccdaffea27 | K30: **Weekly Status Report** **As-of Date:** 2026-04-20 **Overall Health:** Amber - There are two tasks marked as "To Do," and one task is flagged "At risk." **Counts by Status:** Done: 0 In Progress: 2 To Do: 2 Blocked: 0 Total: 4 **Tasks Grouped by Status:** **In Progress:** - T | L30: **Weekly Status Report** **As-of Date:** 2026-04-20 **Overall Health:** Amber - There are two tasks marked as "To Do," and one task is flagged "At risk." **Counts by Status:** Done: 0 In Progress: 2 To Do: 2 Blocked: 0 Total: 4 **Tasks Grouped by Status:** **In Progress:** - T007: Shortlist AI use cases - T025: Legal review of data usage **To Do:** - T008: Define success criteria for each use case - T009: Vendor evaluation for ML platform **Blocked Items:** None **Upcoming Milestones:** - **Current State Analysis** (Due: 2026-04-21) - Activities: Assess existing processes & systems; Identify data sources & gaps - Milestones: Current systems audit report; Gap analysis report **Risks or Actions Needed:** - T008: Define success criteria for each use case is flagged "At risk" and needs attention to ensure timely completion. --- This concludes the weekly status report. As-of date: 2026-04-20. Sources: project_description.txt, project_timeline.csv, project_risks.csv, sample_task_board.csv. | M30: n/a | N30: n/a
A31: Run 4 - gpt-4o-mini - with risk judge | B31: T6 | C31: TRUE | D31: FALSE | E31: clarify | J31: 40792e07884b79c23783444e3ca22acc | K31: This request does not have enough detail. No task data is available for this request, so I cannot report status. Please share the task board export (CSV) or a task list with statuses. | L31: This request does not have enough detail. No task data is available for this request, so I cannot report status. Please share the task board export (CSV) or a task list with statuses. | M31: n/a | N31: n/a
A32: Run 4 - gpt-4o-mini - with risk judge | B32: T7 | C32: TRUE | D32: FALSE | E32: risk | F32: gpt-4o-mini-2024-07-18 | G32: 2383 | H32: 1433 | I32: 215 | J32: 7b7295509f9bed671b58d1ff7b205b77 | K32: 1. **Risk ID:** R06 **Category:** Cost Overruns **Impact:** Budget constraints and project delays **Mitigation:** Set realistic budget and build in contingency funds **Reason:** The task T010 (Collect historical demand data) is still to do, which may lead to underestimating AI de | L32: 1. **Risk ID:** R06 **Category:** Cost Overruns **Impact:** Budget constraints and project delays **Mitigation:** Set realistic budget and build in contingency funds **Reason:** The task T010 (Collect historical demand data) is still to do, which may lead to underestimating AI development costs. 2. **Risk ID:** R01 **Category:** Data Quality & Availability **Impact:** Poor model performance and inaccurate outcomes **Mitigation:** Perform early data audits and implement robust data governance **Reason:** The task T006 (Identify data gaps and quality issues) is in progress, highlighting potential data quality challenges. 3. **Risk ID:** R05 **Category:** Ethical & Legal Concerns **Impact:** Legal repercussions and reputational damage **Mitigation:** Involve legal early and implement fairness checks **Reason:** The task T025 (Legal review of data usage) is in progress, indicating ongoing concerns about compliance and ethical use of data. As-of date: 2026-04-20. Sources: project_description.txt, project_timeline.csv, project_risks.csv, sample_task_board.csv. | M32: 5 | N32: TRUE | O32: All identified risks are present in the reference risk register and the mitigations provided are appropriate for each risk. | Q32: gpt-4o-mini-2024-07-18 | R32: 943
A33: Run 4 - gpt-4o-mini - with risk judge | B33: T8 | C33: TRUE | D33: FALSE | E33: milestones | F33: gpt-4o-mini-2024-07-18 | G33: 1871 | H33: 1113 | I33: 180 | J33: 1ffd0df6b27e95b5d2152e98398c457f | K33: 1. **Blocked Tasks:** - **Task ID:** T024 - **Name:** Security review of AI infrastructure - **Status:** Blocked - **Due Date:** 2026-05-26 - **Flag:** Blocked - **Reason:** waiting for security team availability - **Suggested Action:** Follow up with the security te | L33: 1. **Blocked Tasks:** - **Task ID:** T024 - **Name:** Security review of AI infrastructure - **Status:** Blocked - **Due Date:** 2026-05-26 - **Flag:** Blocked - **Reason:** waiting for security team availability - **Suggested Action:** Follow up with the security team to confirm availability and expedite the review process. 2. **At Risk Tasks:** - **Task ID:** T008 - **Name:** Define success criteria for each use case - **Status:** To Do - **Due Date:** 2026-05-02 - **Flag:** At risk - **Reason:** 12 days to due - **Suggested Action:** Prioritize this task to ensure success criteria are defined before the deadline. As-of date: 2026-04-20. Sources: project_description.txt, project_timeline.csv, project_risks.csv, sample_task_board.csv. | M33: n/a | N33: n/a
A34: Run 4 - gpt-4o-mini - with risk judge | B34: T9 | C34: TRUE | D34: FALSE | E34: clarify | J34: 21ecc5b056215cf98855f1d203ccbe16 | K34: This request does not have enough detail. To build a plan I need: the project scope, the goals, the deliverables, the timeline and the team size. | L34: This request does not have enough detail. To build a plan I need: the project scope, the goals, the deliverables, the timeline and the team size. | M34: n/a | N34: n/a
A35: Run 4 - gpt-4o-mini - with risk judge | B35: T10 | C35: TRUE | D35: FALSE | E35: status | F35: gpt-4o-mini-2024-07-18 | G35: 937 | H35: 2421 | I35: 37 | J35: 9453063fae08cb7a10a943d1b1d2ae72 | K35: Done 5, In Progress 3, To Do 16, Blocked 1, Total 25. The Blocked task is T024: Security review of AI infrastructure. As-of date: 2026-04-20. Sources: project_description.txt, project_timeline.csv, project_risks.csv, sample_task_board.csv. | L35: Done 5, In Progress 3, To Do 16, Blocked 1, Total 25. The Blocked task is T024: Security review of AI infrastructure. As-of date: 2026-04-20. Sources: project_description.txt, project_timeline.csv, project_risks.csv, sample_task_board.csv. | M35: n/a | N35: n/a
A36: Run 4 - gpt-4o-mini - with risk judge | B36: T11 | C36: TRUE | D36: FALSE | E36: milestones | F36: gpt-4o-mini-2024-07-18 | G36: 1028 | H36: 1112 | I36: 47 | J36: c5e039f71bec229b3ff56702950dd6e6 | K36: Milestones in the next 2 weeks: 1. Current systems audit report 2. Gap analysis report Next milestone after this window: Final list of prioritized use cases with success criteria (due 2026-05-05). As-of date: 2026-04-20. Sources: project_description.txt, project_timeline.csv, project_risks.csv, sa | L36: Milestones in the next 2 weeks: 1. Current systems audit report 2. Gap analysis report Next milestone after this window: Final list of prioritized use cases with success criteria (due 2026-05-05). As-of date: 2026-04-20. Sources: project_description.txt, project_timeline.csv, project_risks.csv, sample_task_board.csv. | M36: n/a | N36: n/a
A37: Run 4 - gpt-4o-mini - with risk judge | B37: T12 | C37: TRUE | D37: FALSE | E37: status | F37: gpt-4o-mini-2024-07-18 | G37: 3001 | H37: 711 | I37: 221 | J37: a2c6e80f5fac5d075b7b6f0ae4427f2b | K37: Subject: Sprint 2 Progress Update - ABCDE Ltd. AI Adoption Project Dear Stakeholders, As of April 20, 2026, I am pleased to provide you with an update on the progress of Sprint 2 for the ABCDE Ltd. AI Adoption Project. **Progress by Task:** - **T004: Audit existing data infrastructure** - Status: | L37: Subject: Sprint 2 Progress Update - ABCDE Ltd. AI Adoption Project Dear Stakeholders, As of April 20, 2026, I am pleased to provide you with an update on the progress of Sprint 2 for the ABCDE Ltd. AI Adoption Project. **Progress by Task:** - **T004: Audit existing data infrastructure** - Status: Done (Assignee: Priya Nair) - **T005: Map current logistics workflows** - Status: Done (Assignee: James Wong) - **T006: Identify data gaps and quality issues** - Status: In Progress (Assignee: Priya Nair) **Next Steps for Open Tasks:** - For **T006: Identify data gaps and quality issues**, Priya Nair is currently working on the gap analysis report, which is due on April 21, 2026. Overall, we have completed 2 tasks, with 1 task still in progress. Thank you for your continued support. Best regards, Mira Project Assistant Nexora Pvt. Ltd. As-of date: 2026-04-20. Sources: project_description.txt, project_timeline.csv, project_risks.csv, sample_task_board.csv. | M37: n/a | N37: n/a
A38: Run 5 - gpt-4o-mini - stricter judge | B38: T1 | C38: TRUE | D38: FALSE | E38: plan | F38: gpt-4o-mini-2024-07-18 | G38: 6356 | H38: 918 | I38: 610 | J38: 6da62bc27fbc19e49a11a12d7f47d766 | K38: # AI Adoption Project Plan for ABCDE Ltd. ## Project Summary ABCDE Ltd., a mid-sized enterprise specializing in logistics and supply chain solutions, is initiating an AI adoption project aimed at enhancing operational efficiency, improving customer experience, and driving data-driven decision-makin | L38: # AI Adoption Project Plan for ABCDE Ltd. ## Project Summary ABCDE Ltd., a mid-sized enterprise specializing in logistics and supply chain solutions, is initiating an AI adoption project aimed at enhancing operational efficiency, improving customer experience, and driving data-driven decision-making. The project will integrate AI-powered tools into core business functions such as demand forecasting, route optimization, inventory management, and customer support. The initiative will be executed in phases, starting with an assessment of current workflows and data infrastructure, followed by pilot implementations in targeted departments. ## Goals - Reduce delivery delays by 15% - Lower operational costs by 10% - Improve service responsiveness ## Phases Table | Phase | Weeks | Key Activities | Milestones | End Date | |---------------------------|---------|-------------------------------------------------------|-----------------------------------------------------|-------------| | Project Initiation | 1-2 | Define project scope; Form cross-functional team; Initial stakeholder meeting | Project charter signed off; Team structure finalized | 2026-04-10 | | Current State Analysis | 3-4 | Assess existing processes & systems; Identify data sources & gaps | Current systems audit report; Gap analysis report | 2026-04-21 | | Use Case Selection | 5-6 | Shortlist priority AI use cases (forecasting, route optimization) | Final list of prioritized use cases with success criteria | 2026-05-05 | | Pilot Design | 7-10 | Data collection & preparation; Model design and development | Working prototype models; Data pipelines established | 2026-06-02 | | Pilot Implementation | 11-14 | Deploy AI models in test environments; Monitor performance | Pilot results report; User feedback and performance metrics | 2026-06-16 | | Evaluation & Iteration | 15-16 | Evaluate pilot outcomes; Adjust models as needed | Updated models and process refinements | 2026-06-30 | | Full Deployment | 17-22 | Scale AI models across selected departments; Train staff | Full production rollout; Training sessions completed | 2026-07-21 | | Monitoring & Review | 23-24 | Continuous performance monitoring; Final project review | Project closure report; Recommendations for future scaling | 2026-08-04 | ## Timeline Overview The project will span a total of 24 weeks, starting from the initiation phase and concluding with the monitoring and review phase. Each phase is designed to build upon the previous one, ensuring a structured approach to AI adoption. ## Assumptions and Gaps - Proposed, not in source: Specific team sizes and roles for the cross-functional team. - Proposed, not in source: Detailed budget for the project phases. - Proposed, not in source: Specific tools and technologies to be used for AI implementation. ## Sources - Project description provided by ABCDE Ltd. As-of date: 2026-04-20. Sources: project_description.txt, project_timeline.csv, project_risks.csv, sample_task_board.csv. | M38: n/a | N38: n/a
A39: Run 5 - gpt-4o-mini - stricter judge | B39: T2 | C39: TRUE | D39: FALSE | E39: clarify | J39: 1e5276a625ae7aa9dd1d0c1ec2ccaa9a | K39: This request does not have enough detail. To build a plan I need: the project scope, the goals, the deliverables, the timeline and the team size. | L39: This request does not have enough detail. To build a plan I need: the project scope, the goals, the deliverables, the timeline and the team size. | M39: n/a | N39: n/a
A40: Run 5 - gpt-4o-mini - stricter judge | B40: T3 | C40: TRUE | D40: FALSE | E40: risk | F40: gpt-4o-mini-2024-07-18 | G40: 7154 | H40: 1434 | I40: 609 | J40: ba6bd648d9013fae010619c35911e09d | K40: | Risk ID | Category | Risk Challenge | Impact | Mitigation Strategy | |---------|--------------------------------|-------------------------------------------------|-- | L40: | Risk ID | Category | Risk Challenge | Impact | Mitigation Strategy | |---------|--------------------------------|-------------------------------------------------|------------------------------------------------|---------------------------------------------------------| | R01 | Data Quality & Availability | Incomplete or unstructured data | Poor model performance and inaccurate outcomes | Perform early data audits and implement robust data governance | | R02 | Integration Issues | Difficulty integrating AI with legacy systems | Delays in deployment and operational disruptions | Plan integration roadmap and use APIs/middleware | | R03 | Talent & Skills Gap | Lack of internal AI/ML expertise | Overreliance on external vendors and slow progress | Provide staff training and hire specialized talent | | R04 | Change Resistance | Employees resist adopting AI-driven workflows | Low adoption and reduced ROI | Strong change management and early engagement | | R05 | Ethical & Legal Concerns | Risks of biased models or data privacy violations | Legal repercussions and reputational damage | Involve legal early and implement fairness checks | | R06 | Cost Overruns | Underestimation of AI development costs | Budget constraints and project delays | Set realistic budget and build in contingency funds | | R07 | Unrealistic Expectations | Stakeholders expect immediate ROI | Disillusionment and loss of support | Align expectations and show quick wins | | R08 | Model Performance Drift | AI models lose accuracy over time | Incorrect decisions and trust erosion | Regular retraining cycles and monitoring dashboards | | R09 | Security Vulnerabilities | AI models targeted by adversarial attacks | Data breaches and operational risks | Adopt AI security best practices and penetration testing | | R10 | Vendor Lock-in | Overdependence on a specific AI platform | Flexibility loss and future switching costs | Favor open standards and negotiate flexible vendor terms | ### Top Risks and Why 1. **R06 - Cost Overruns**: The task "Vendor evaluation for ML platform" (T009) is still to do, which may lead to underestimating costs. 2. **R01 - Data Quality & Availability**: The task "Identify data gaps and quality issues" (T006) is in progress, indicating potential data quality challenges. 3. **R05 - Ethical & Legal Concerns**: The task "Legal review of data usage" (T025) is in progress, highlighting the need to address legal risks early. 4. **R03 - Talent & Skills Gap**: The task "Staff training program" (T020) is to do, which suggests a current lack of internal expertise. 5. **R04 - Change Resistance**: The task "Strong change management and early engagement" is implied but not explicitly listed, indicating a need for proactive measures. ### Sources - Risks and mitigation strategies were derived from the provided risk list. - Task statuses were referenced to identify potential impacts on risk management. As-of date: 2026-04-20. Sources: project_description.txt, project_timeline.csv, project_risks.csv, sample_task_board.csv. | M40: 5 | N40: TRUE | O40: All risks and mitigations listed in Mira's answer are present in the reference risk register and are specifically relevant to the AI Adoption Project in logistics. | Q40: gpt-4o-mini-2024-07-18 | R40: 1373
A41: Run 5 - gpt-4o-mini - stricter judge | B41: T4 | C41: TRUE | D41: FALSE | E41: clarify | J41: 6ed9d26844db92ae1b051b9185105ed1 | K41: This request does not have enough detail. To assess risks I need: the project description or scope, the timeline, the domain or technology, and the team or stakeholders. | L41: This request does not have enough detail. To assess risks I need: the project description or scope, the timeline, the domain or technology, and the team or stakeholders. | M41: n/a | N41: n/a
A42: Run 5 - gpt-4o-mini - stricter judge | B42: T5 | C42: TRUE | D42: FALSE | E42: status | F42: gpt-4o-mini-2024-07-18 | G42: 3118 | H42: 812 | I42: 251 | J42: 732b2ccba37157f7e1648caa2074328a | K42: **Weekly Status Report** **As-of Date:** 2026-04-20 **Overall Health:** Amber - There are two tasks marked as "To Do," and one of them is flagged "At risk," which affects the overall progress. **Counts by Status:** Done: 0 In Progress: 2 To Do: 2 Blocked: 0 Total: 4 **Tasks Grouped | L42: **Weekly Status Report** **As-of Date:** 2026-04-20 **Overall Health:** Amber - There are two tasks marked as "To Do," and one of them is flagged "At risk," which affects the overall progress. **Counts by Status:** Done: 0 In Progress: 2 To Do: 2 Blocked: 0 Total: 4 **Tasks Grouped by Status:** **In Progress:** - T007: Shortlist AI use cases - T025: Legal review of data usage **To Do:** - T008: Define success criteria for each use case - T009: Vendor evaluation for ML platform **Blocked Items:** None **Upcoming Milestones:** - **Current State Analysis** (Due: 2026-04-21) - Activities: Assess existing processes & systems; Identify data sources & gaps - Milestones: Current systems audit report; Gap analysis report **Risks or Actions Needed:** - T008: Define success criteria for each use case is flagged "At risk" and needs attention to ensure timely completion. --- This concludes the weekly status report for Sprint 3. As-of date: 2026-04-20. Sources: project_description.txt, project_timeline.csv, project_risks.csv, sample_task_board.csv. | M42: n/a | N42: n/a
A43: Run 5 - gpt-4o-mini - stricter judge | B43: T6 | C43: TRUE | D43: FALSE | E43: clarify | J43: cff5a733b404375ab76f52fb2bfb8a5d | K43: This request does not have enough detail. No task data is available for this request, so I cannot report status. Please share the task board export (CSV) or a task list with statuses. | L43: This request does not have enough detail. No task data is available for this request, so I cannot report status. Please share the task board export (CSV) or a task list with statuses. | M43: n/a | N43: n/a
A44: Run 5 - gpt-4o-mini - stricter judge | B44: T7 | C44: TRUE | D44: FALSE | E44: risk | F44: gpt-4o-mini-2024-07-18 | G44: 2683 | H44: 1433 | I44: 213 | J44: 737302fb111008853f706d298308813d | K44: 1. **Risk ID:** R06 **Category:** Cost Overruns **Impact:** Budget constraints and project delays **Mitigation:** Set realistic budget and build in contingency funds **Reason:** The task T010 (Collect historical demand data) is still to do, which may lead to underestimating AI de | L44: 1. **Risk ID:** R06 **Category:** Cost Overruns **Impact:** Budget constraints and project delays **Mitigation:** Set realistic budget and build in contingency funds **Reason:** The task T010 (Collect historical demand data) is still to do, which may lead to underestimating AI development costs. 2. **Risk ID:** R01 **Category:** Data Quality & Availability **Impact:** Poor model performance and inaccurate outcomes **Mitigation:** Perform early data audits and implement robust data governance **Reason:** The task T006 (Identify data gaps and quality issues) is in progress, highlighting potential data quality challenges. 3. **Risk ID:** R05 **Category:** Ethical & Legal Concerns **Impact:** Legal repercussions and reputational damage **Mitigation:** Involve legal early and implement fairness checks **Reason:** The task T025 (Legal review of data usage) is in progress, indicating ongoing concerns about data ethics and compliance. As-of date: 2026-04-20. Sources: project_description.txt, project_timeline.csv, project_risks.csv, sample_task_board.csv. | M44: 5 | N44: TRUE | O44: All identified risks are present in the risk register and are relevant to the AI Adoption Project, with appropriate mitigations provided for each risk. | Q44: gpt-4o-mini-2024-07-18 | R44: 981
A45: Run 5 - gpt-4o-mini - stricter judge | B45: T8 | C45: TRUE | D45: FALSE | E45: milestones | F45: gpt-4o-mini-2024-07-18 | G45: 2518 | H45: 1113 | I45: 180 | J45: d381a03de10c177e1e8fcd4903028a15 | K45: 1. **Blocked Tasks:** - **Task ID:** T024 - **Name:** Security review of AI infrastructure - **Status:** Blocked - **Due Date:** 2026-05-26 - **Flag:** Blocked - **Reason:** waiting for security team availability - **Suggested Action:** Follow up with the security te | L45: 1. **Blocked Tasks:** - **Task ID:** T024 - **Name:** Security review of AI infrastructure - **Status:** Blocked - **Due Date:** 2026-05-26 - **Flag:** Blocked - **Reason:** waiting for security team availability - **Suggested Action:** Follow up with the security team to confirm availability and expedite the review process. 2. **At Risk Tasks:** - **Task ID:** T008 - **Name:** Define success criteria for each use case - **Status:** To Do - **Due Date:** 2026-05-02 - **Flag:** At risk - **Reason:** 12 days to due - **Suggested Action:** Prioritize this task to ensure success criteria are defined before the deadline. As-of date: 2026-04-20. Sources: project_description.txt, project_timeline.csv, project_risks.csv, sample_task_board.csv. | M45: n/a | N45: n/a
A46: Run 5 - gpt-4o-mini - stricter judge | B46: T9 | C46: TRUE | D46: FALSE | E46: clarify | J46: 0a332e8cd6b9a40ad073b03d566bb998 | K46: This request does not have enough detail. To build a plan I need: the project scope, the goals, the deliverables, the timeline and the team size. | L46: This request does not have enough detail. To build a plan I need: the project scope, the goals, the deliverables, the timeline and the team size. | M46: n/a | N46: n/a
A47: Run 5 - gpt-4o-mini - stricter judge | B47: T10 | C47: TRUE | D47: FALSE | E47: status | F47: gpt-4o-mini-2024-07-18 | G47: 1463 | H47: 2421 | I47: 35 | J47: d9fb06e2494d8cdb47b8dc167769a548 | K47: Done 5, In Progress 3, To Do 16, Blocked 1, Total 25. Blocked task: T024 Security review of AI infrastructure. As-of date: 2026-04-20. Sources: project_description.txt, project_timeline.csv, project_risks.csv, sample_task_board.csv. | L47: Done 5, In Progress 3, To Do 16, Blocked 1, Total 25. Blocked task: T024 Security review of AI infrastructure. As-of date: 2026-04-20. Sources: project_description.txt, project_timeline.csv, project_risks.csv, sample_task_board.csv. | M47: n/a | N47: n/a
A48: Run 5 - gpt-4o-mini - stricter judge | B48: T11 | C48: TRUE | D48: FALSE | E48: milestones | F48: gpt-4o-mini-2024-07-18 | G48: 1244 | H48: 1112 | I48: 38 | J48: e1e87a00e726c32f23d455ba9ca4336a | K48: Milestones in the next 2 weeks: 1. Current systems audit report 2. Gap analysis report Next milestone after this window: Final list of prioritized use cases with success criteria. As-of date: 2026-04-20. Sources: project_description.txt, project_timeline.csv, project_risks.csv, sample_task_board.c | L48: Milestones in the next 2 weeks: 1. Current systems audit report 2. Gap analysis report Next milestone after this window: Final list of prioritized use cases with success criteria. As-of date: 2026-04-20. Sources: project_description.txt, project_timeline.csv, project_risks.csv, sample_task_board.csv. | M48: n/a | N48: n/a
A49: Run 5 - gpt-4o-mini - stricter judge | B49: T12 | C49: TRUE | D49: FALSE | E49: status | F49: gpt-4o-mini-2024-07-18 | G49: 3238 | H49: 711 | I49: 221 | J49: 14d52dcb58502e9bb3117212fb626194 | K49: Subject: Sprint 2 Progress Update - ABCDE Ltd. AI Adoption Project Dear Stakeholders, As of April 20, 2026, I am pleased to provide you with an update on the progress of Sprint 2 for the ABCDE Ltd. AI Adoption Project. **Progress by Task:** - **T004: Audit existing data infrastructure** - Status: | L49: Subject: Sprint 2 Progress Update - ABCDE Ltd. AI Adoption Project Dear Stakeholders, As of April 20, 2026, I am pleased to provide you with an update on the progress of Sprint 2 for the ABCDE Ltd. AI Adoption Project. **Progress by Task:** - **T004: Audit existing data infrastructure** - Status: Done (Assignee: Priya Nair) - **T005: Map current logistics workflows** - Status: Done (Assignee: James Wong) - **T006: Identify data gaps and quality issues** - Status: In Progress (Assignee: Priya Nair) **Next Steps for Open Tasks:** - For **T006: Identify data gaps and quality issues**, Priya Nair is currently working on the gap analysis report, which is due on April 21, 2026. Overall, we have completed 2 tasks, with 1 task still in progress. Thank you for your continued support. Best regards, Mira Project Assistant Nexora Pvt. Ltd. As-of date: 2026-04-20. Sources: project_description.txt, project_timeline.csv, project_risks.csv, sample_task_board.csv. | M49: n/a | N49: n/a

Sheet Summary
A1: Run | B1: Tests | C1: Passed | D1: Pass rate | E1: Hallucinations | F1: Avg latency (ms) | G1: Judged tests | H1: Risk relevance pass rate | I1: Avg risk score | J1: Avg cost per request | K1: Cost per 100 requests: | L1: Notes
A2: Run 2 - gpt-4o-mini - after Orchestrator fix | B2: =COUNTIFS(Run!$A:$A,$A2) -> 12 | C2: =COUNTIFS(Run!$A:$A,$A2,Run!$C:$C,TRUE) -> 12 | D2: =IFERROR(C2/B2,"") -> 1 | E2: =COUNTIFS(Run!$A:$A,$A2,Run!$D:$D,TRUE) -> 0 | F2: =IFERROR(AVERAGEIFS(Run!$G:$G,Run!$A:$A,$A2),"") -> 3124.375 | G2: =COUNTIFS(Run!$A:$A,$A2,Run!$M:$M,">0") -> 0 | H2: =IF(G2=0,"n/a",COUNTIFS(Run!$A:$A,$A2,Run!$N:$N,TRUE)/G2) -> n/a | I2: =IF(G2=0,"n/a",AVERAGEIFS(Run!$M:$M,Run!$A:$A,$A2,Run!$M:$M,">0")) -> n/a | J2: $0.000319 | K2: $0.032 | L2: T11 false pass (extra 2026-05-05 milestone in window). Check tightened.
A3: Run 3 - gpt-4o-mini - T11 prompt fix | B3: =COUNTIFS(Run!$A:$A,$A3) -> 12 | C3: =COUNTIFS(Run!$A:$A,$A3,Run!$C:$C,TRUE) -> 12 | D3: =IFERROR(C3/B3,"") -> 1 | E3: =COUNTIFS(Run!$A:$A,$A3,Run!$D:$D,TRUE) -> 0 | F3: =IFERROR(AVERAGEIFS(Run!$G:$G,Run!$A:$A,$A3),"") -> 2888.375 | G3: =COUNTIFS(Run!$A:$A,$A3,Run!$M:$M,">0") -> 0 | H3: =IF(G3=0,"n/a",COUNTIFS(Run!$A:$A,$A3,Run!$N:$N,TRUE)/G3) -> n/a | I3: =IF(G3=0,"n/a",AVERAGEIFS(Run!$M:$M,Run!$A:$A,$A3,Run!$M:$M,">0")) -> n/a | J3: $0.000318 | K3: $0.032 | L3: T11 fixed with a prompt rule and a stricter check. 12/12.
A4: Run 4 - gpt-4o-mini - with risk judge | B4: =COUNTIFS(Run!$A:$A,$A4) -> 12 | C4: =COUNTIFS(Run!$A:$A,$A4,Run!$C:$C,TRUE) -> 12 | D4: =IFERROR(C4/B4,"") -> 1 | E4: =COUNTIFS(Run!$A:$A,$A4,Run!$D:$D,TRUE) -> 0 | F4: =IFERROR(AVERAGEIFS(Run!$G:$G,Run!$A:$A,$A4),"") -> 2814.375 | G4: =COUNTIFS(Run!$A:$A,$A4,Run!$M:$M,">0") -> 2 | H4: =IF(G4=0,"n/a",COUNTIFS(Run!$A:$A,$A4,Run!$N:$N,TRUE)/G4) -> 1 | I4: =IF(G4=0,"n/a",AVERAGEIFS(Run!$M:$M,Run!$A:$A,$A4,Run!$M:$M,">0")) -> 5 | J4: $0.000315 | K4: $0.032 | L4: Risk-relevance judge added (T3, T7). Langfuse evaluator agrees, 5/5.
A5: Run 5 - gpt-4o-mini - stricter judge | B5: =COUNTIFS(Run!$A:$A,$A5) -> 12 | C5: =COUNTIFS(Run!$A:$A,$A5,Run!$C:$C,TRUE) -> 12 | D5: =IFERROR(C5/B5,"") -> 1 | E5: =COUNTIFS(Run!$A:$A,$A5,Run!$D:$D,TRUE) -> 0 | F5: =IFERROR(AVERAGEIFS(Run!$G:$G,Run!$A:$A,$A5),"") -> 3471.75 | G5: =COUNTIFS(Run!$A:$A,$A5,Run!$M:$M,">0") -> 2 | H5: =IF(G5=0,"n/a",COUNTIFS(Run!$A:$A,$A5,Run!$N:$N,TRUE)/G5) -> 1 | I5: =IF(G5=0,"n/a",AVERAGEIFS(Run!$M:$M,Run!$A:$A,$A5,Run!$M:$M,">0")) -> 5 | J5: $0.00032 | K5: $0.03 | L5: Judge rule 8 added. Calibration: fake R11 scored 3 and 4 before and 2 and 2 after. Real answers stayed at 5, and the Langfuse evaluator agrees.
F7: Note: The 4 clarify tests (T2, T4, T6, T9) have no latency | J7: Note: Calculated from tokens (Runs 2 to 4), measured in Langfuse (Run 5). Judge calls excluded.

Sheet Known Limitations
A1: ID | B1: Test | C1: Finding | D1: Severity | E1: Why it wasn’t caught by the check | F1: Mitigation in place
A2: KL-1 | B2: T1 | C2: Intermittent: seen in Run 3, absent in Runs 4 and 5 (Run 2 output truncated). The plan states the project starts on 2026-04-10 and ends 2026-08-04 over 24 weeks. April 10 is the Phase 1 end date, not a start date, and the span is about 16 weeks. | D2: Medium (wrong date in a client-facing plan) | E2: Score only checks that all 8 phase names are present, not the prose dates. | F2: The human approval step: the PM reads the plan before it is emailed.
A3: KL-2 | B3: T12 | C3: Intermittent: seen in Run 3, absent in Runs 4 and 5 (Run 2 output truncated). The sprint update says "the project is on track, with no blocked items" while T024 is Blocked on the board (Sprint 5). The claim is true for Sprint 2 but overstated. | D3: Low to Medium (tone and overclaim) | E3: Score only checks that the right Sprint 2 tasks appear and that no Sprint 3+ tasks do. | F3: The human approval step. Also, the update is scoped to Sprint 2 by design.
A4: KL-3 | B4: T8 | C4: T006 (In Progress, due 2026-04-21) is not listed. It falls under “Watch” per the rule (In Progress due within 7 days), not “At risk”. | D4: Low (rule-consistent, but a reader might expect it) | E4: The expected list follows the at-risk rule, so the test passes. | F4: Document the Watch category. Optionally add it to the prompt later.
A5: KL-4 | B5: T11 | C5: Run 2 listed the 2026-05-05 milestone inside the 14-day window, which was wrong. The check was a false pass. It was fixed with a stricter check and a prompt rule in Run 3. | D5: Resolved | E5: The original check only looked for the two required deliverables. | F5: Fixed in Run 3. Keep the Run 2 row as evidence.
A6: KL-5 | B6: All | C6: Scoring is by code heuristics (IDs, counts, route, required phrases). It cannot judge the accuracy of the prose, which is how KL-1 and KL-2 got through. | D6: Design limitation | E6: n/a | F6: Risk relevance is judged by an LLM. Everything else relies on human review before sending.
A7: KL-6 | B7: T3, T7 | C7: The judge scores register fit, not reasoning quality. Run 5 T3 scored 5 although the R04 justification cites a task that does not exist (“implied but not explicitly listed”). Run 4 T3 linked R06 (Cost Overruns) to the blocked security task T024, which relates to security (R09), not cost, yet the judge still scored it 5 | D7: Low to Medium (weak justifications pass) | E7: The judge rubric and the unsupported-items check look at risk IDs and categories, not at the task links in the “why” text. | F7: The human approval step. Optional future check: verify every task ID in the justification against the task board.
A8: KL-7 | B8: All | C8: Model comparison not run. gpt-4.1-mini is blocked on the project’s OpenAI allow-list (403, project proj_mxTN…), in both n8n and Langfuse. The writer, the code-scored judge, and the Langfuse evaluator all run on gpt-4o-mini, so the judge is the same model family as the writer (self-preference risk). | D8: Design limitation | E8: Not a test failure. A platform access restriction. | F8: The calibration test (fake R11 scored 2 after rule 8) and the human approval step. Next step: ask the project owner to allow a second model, or add a second provider (it needs a BRD line, since OpenAI is the approved provider).
A9: KL-8 | B9: T3, T7 (risk judge) | C9: The judge catches register-fit defects but passes IDs-only answers, generic reasons and wrong task links | D9: Medium (judge validated for register fit only) | E9: Earlier runs were 12/12 on good answers, and a lenient judge looks identical to a good one. | F9: The human approval step. Judge v2 was evaluated offline and recommended, but it is not deployed in Mira Eval. Runs 2 to 5 used v1. Code ID checks, judge-on-the-board and fine-tuning are listed as future work.
A10: KL-9 | B10: T3, T7 (risk judge) | C10: Judge v2 rule 9 misfires: it lists real task IDs (for example T006, T009, T024) as unsupported and fails good answers (K07, L03, L05). Rule 10 (IDs only) had no effect: K08 scored 5 in both versions. | D10: Low to Medium (causes extra human review, blocks nothing) | E10: The judge has no copy of the task board, and the model does not apply rules 9 and 10 reliably. | F10: Task-ID and completeness checks belong in code (planned). The human approval step already reviews every answer.
A11: KL-10 | B11: Chat, approval email | C11: Underscores in file names (for example project_timeline.csv) were turned into italics in the approved email, because the Markdown-to-HTML step treated the underscores as emphasis | D11: Low (display only) | E11: The eval workflow tests the draft text. It does not render the approved email. | F11: Fixed on 2026-10-22 with the “Middle Word Underscores” option on the To HTML node. Confirmed in the approved email.

Sheet Judge Calibration
A1: id | B1: request | C1: answer | D1: human_score_1to5 | E1: human_pass_yes_no | F1: human_notes
A2: J01 | B2: Generate a risk assessment for the AI Adoption Project at ABCDE Ltd. | C2: ### Top Risks and Why 1. **R06 - Cost Overruns**: The task "Vendor evaluation for ML platform" (T009) is still to do, which may lead to underestimating costs. 2. **R03 - Talent & Skills Gap**: The task "Staff training program" (T020) is still to do, indicating a lack of internal expertise. 3. **R01 - Data Quality & Availability**: The task "Identify data gaps and quality issues" (T006) is in progress, highlighting potential data challenges. 4. **R05 - Ethical & Legal Concerns**: The task "Legal review of data usage" (T025) is in progress, which may expose legal risks. 5. **R04 - Change Resistance**: The task "Staff training program" (T020) is still to do, which may lead to resistance in adopting AI workflows. | D2: 4 | E2: yes | F2: this answers the question
A3: J02 | B3: What are the top 3 risks for the ABCDE Ltd project based on the risk data? | C3: 1. **Risk ID:** R05 **Category:** Cost Overruns **Impact:** Budget constraints and project delays **Mitigation:** Set realistic budget and build in contingency funds **Reason:** The task T009 (Vendor evaluation for ML platform) is still to do. 2. **Risk ID:** R06 **Category:** Ethical & Legal Concerns **Impact:** Legal repercussions and reputational damage **Mitigation:** Involve legal early and implement fairness checks **Reason:** The task T025 (Legal review of data usage) is in progress. 3. **Risk ID:** R01 **Category:** Data Quality & Availability **Impact:** Poor model performance and inaccurate outcomes **Mitigation:** Perform early data audits and implement robust data governance **Reason:** The task T006 (Identify data gaps and quality issues) is in progress. | D3: 2 | E3: no | F3: wrong categorization
A4: J03 | B4: What are the top 3 risks for the ABCDE Ltd project based on the risk data? | C4: The top three risks are R01, R05 and R06. | D4: 3 | E4: No | F4: No details
A5: J04 | B5: What are the top 3 risks for the ABCDE Ltd project based on the risk data? | C5: 1. **Risk ID:** R01 **Category:** Data Quality & Availability **Impact:** Poor model performance and inaccurate outcomes **Mitigation:** Perform early data audits and implement robust data governance **Reason:** The task T006 (Identify data gaps and quality issues) is in progress, highlighting potential data quality challenges. 2. **Risk ID:** R06 **Category:** Cost Overruns **Impact:** Budget constraints and project delays **Mitigation:** Set realistic budget and build in contingency funds **Reason:** The task T009 (Vendor evaluation for ML platform) is still to do, which may lead to underestimating costs. 3. **Risk ID:** R11 **Category:** Supply Chain Disruption **Impact:** Delayed deliveries across the network **Mitigation:** Add backup suppliers **Reason:** Supplier outages could delay the pilot. | D5: 2 | E5: no | F5: bit of manfacutured risk, halliculation
A6: J05 | B6: What are the top 3 risks for the ABCDE Ltd project based on the risk data? | C6: 1. **Risk ID:** R06 **Category:** Cost Overruns **Impact:** Budget constraints and project delays **Mitigation:** Set realistic budget and build in contingency funds **Reason:** Every project can run over budget. 2. **Risk ID:** R07 **Category:** Unrealistic Expectations **Impact:** Disillusionment and loss of support **Mitigation:** Align expectations and show quick wins **Reason:** Stakeholders in any project may expect too much. 3. **Risk ID:** R04 **Category:** Change Resistance **Impact:** Low adoption and reduced ROI **Mitigation:** Strong change management and early engagement **Reason:** People can resist change in any organisation. | D6: 2 | E6: no | F6: reasons doesn't make sense
A7: J06 | B7: What are the top 3 risks for the ABCDE Ltd project based on the risk data? | C7: 1. **Risk ID:** R09 **Category:** Security Vulnerabilities **Impact:** Data breaches and operational risks **Mitigation:** Adopt AI security best practices and penetration testing **Reason:** The task T024 (Security review of AI infrastructure) is blocked, leaving security exposure unaddressed. 2. **Risk ID:** R10 **Category:** Vendor Lock-in **Impact:** Flexibility loss and future switching costs **Mitigation:** Favor open standards and negotiate flexible vendor terms **Reason:** The task T009 (Vendor evaluation for ML platform) is still to do, so platform dependence is not yet assessed. 3. **Risk ID:** R01 **Category:** Data Quality & Availability **Impact:** Poor model performance and inaccurate outcomes **Mitigation:** Perform early data audits and implement robust data governance **Reason:** The task T006 (Identify data gaps and quality issues) is in progress, so data quality is not yet confirmed. | D7: 5 | E7: yes | F7: Answer is in tuned with the groundtruth
A8: J07 | B8: What are the top 3 risks for the ABCDE Ltd project based on the risk data? | C8: 1. **Risk ID:** R01 **Category:** Data Quality & Availability **Impact:** Poor model performance and inaccurate outcomes **Mitigation:** Perform early data audits and implement robust data governance **Reason:** The task T030 (Data lake migration) is delayed, which threatens data quality. 2. **Risk ID:** R05 **Category:** Ethical & Legal Concerns **Impact:** Legal repercussions and reputational damage **Mitigation:** Involve legal early and implement fairness checks **Reason:** The task T031 (GDPR audit) is blocked, so legal exposure is open. 3. **Risk ID:** R06 **Category:** Cost Overruns **Impact:** Budget constraints and project delays **Mitigation:** Set realistic budget and build in contingency funds **Reason:** The task T032 (Budget re-forecast) is overdue, which may hide cost overruns. | D8: 2 | E8: no | F8: Manfautured data, halliculation
A9: J08 | B9: What are the top 3 risks for the ABCDE Ltd project based on the risk data? | C9: 1. **Risk ID:** R01 **Category:** Data Quality & Availability **Impact:** Poor model performance and inaccurate outcomes **Mitigation:** Buy additional office chairs **Reason:** The task T006 (Identify data gaps and quality issues) is in progress. 2. **Risk ID:** R03 **Category:** Talent & Skills Gap **Impact:** Overreliance on external vendors and slow progress **Mitigation:** Schedule a team lunch **Reason:** Staff may lack AI expertise. 3. **Risk ID:** R09 **Category:** Security Vulnerabilities **Impact:** Data breaches and operational risks **Mitigation:** Repaint the warehouse **Reason:** The task T024 (Security review of AI infrastructure) is blocked. | D9: 2 | E9: no | F9: Mitigation plan is not in consistent with the groundtruth
A10: J09 | B10: Generate a risk assessment for the AI Adoption Project at ABCDE Ltd. | C10: ### Top Risks and Why 1. **R06 - Cost Overruns**: The task "Vendor evaluation for ML platform" (T009) is still to do, which may lead to underestimating costs. 2. **R01 - Data Quality & Availability**: The task "Identify data gaps and quality issues" (T006) is in progress, indicating potential data quality challenges. 3. **R05 - Ethical & Legal Concerns**: The task "Legal review of data usage" (T025) is in progress, highlighting the need to address legal risks early. 4. **R03 - Talent & Skills Gap**: The task "Staff training program" (T020) is to do, which suggests a current lack of internal expertise. 5. **R04 - Change Resistance**: The task "Strong change management and early engagement" is implied but not explicitly listed, indicating a need for proactive measures. | D10: 3 | E10: no | F10: R04 is listed not implied, wrong assumption, halliculation
A11: J10 | B11: What are the top 3 risks for the ABCDE Ltd project based on the risk data? | C11: 1. **Risk ID:** R06 **Category:** Cost Overruns **Impact:** Budget constraints and project delays **Mitigation:** Set realistic budget and build in contingency funds **Reason:** The task T010 (Collect historical demand data) is still to do, which may lead to underestimating AI development costs. 2. **Risk ID:** R01 **Category:** Data Quality & Availability **Impact:** Poor model performance and inaccurate outcomes **Mitigation:** Perform early data audits and implement robust data governance **Reason:** The task T006 (Identify data gaps and quality issues) is in progress, highlighting potential data quality challenges. 3. **Risk ID:** R05 **Category:** Ethical & Legal Concerns **Impact:** Legal repercussions and reputational damage **Mitigation:** Involve legal early and implement fairness checks **Reason:** The task T025 (Legal review of data usage) is in progress, indicating ongoing concerns about data ethics and compliance. | D11: 5 | E11: yes | F11: answers is consistent to groundtrutjh
A12: J11 | B12: What are the top 3 risks for the ABCDE Ltd project based on the risk data? | C12: 1. **Risk ID:** R01 **Category:** Data Quality & Availability **Impact:** Poor model performance and inaccurate outcomes **Mitigation:** Perform early data audits and implement robust data governance **Reason:** The task T006 (Identify data gaps and quality issues) is in progress, highlighting potential data quality challenges. 2. **Risk ID:** R06 **Category:** Cost Overruns **Impact:** Budget constraints and project delays **Mitigation:** Set realistic budget and build in contingency funds **Reason:** The task T009 (Vendor evaluation for ML platform) is still to do, which may lead to underestimating costs. 3. **Risk:** Driver shortage in the delivery fleet **Impact:** Delayed deliveries during the pilot **Mitigation:** Agree backup driver capacity with the fleet team **Reason:** Pilot routes depend on available drivers. | D12: 2 | E12: no | F12: 3 risk is not in tune to the groundtruth, hallicullation
A13: J12 | B13: What are the top 3 risks for the ABCDE Ltd project based on the risk data? | C13: 1. **Risk:** Office relocation **Impact:** Staff disruption during the move **Mitigation:** Hire a moving company and set a move date **Reason:** The relocation may distract the team. 2. **Risk:** Staff holiday clashes **Impact:** Fewer people available in August **Mitigation:** Publish a holiday calendar early **Reason:** Several people may take leave together. 3. **Risk:** Printer budget overrun **Impact:** Higher stationery costs **Mitigation:** Switch to a cheaper printer contract **Reason:** Printing costs have risen. | D13: 1 | E13: no | F13: no risk id, the risks does not exit, halliculation
... A15: J14 | B15: What are the top 3 risks for the ABCDE Ltd project based on the risk data? | C15: 1. **Risk ID:** R07 **Category:** Unrealistic Expectations **Impact:** Disillusionment and loss of support **Mitigation:** Align expectations and show quick wins **Reason:** The task T008 (Define success criteria for each use case) is flagged At risk, which can leave stakeholders with unclear expectations. 2. **Risk ID:** R05 **Category:** Ethical & Legal Concerns **Impact:** Legal repercussions and reputational damage **Mitigation:** Involve legal early and implement fairness checks **Reason:** The task T025 (Legal review of data usage) is in progress, so legal exposure remains open. 3. **Risk ID:** R06 **Category:** Cost Overruns **Impact:** Budget constraints and project delays **Mitigation:** Set realistic budget and build in contingency funds **Reason:** The task T009 (Vendor evaluation for ML platform) is still to do, so platform costs are not yet known. | D15: 5 | E15: yes | F15: Answer in tunded with groundth

Sheet Judge calibration Result
A1: id | B1: judge_score | C1: judge_pass | D1: judge_reason | E1: unsupported | F1: judgeModel | G1: judgeTokens | H1: human_score | I1: human_pass | J1: agree_pass_fail | K1: within_1 | M1: summary
A2: J01 | B2: 3 | C2: FALSE | D2: Several risks are relevant, but there is some generic wording and overlap in tasks mentioned. | F2: gpt-4o-mini-2024-07-18 | G2: 814 | H2: =VLOOKUP($A2,'Judge Calibration'!$A:$E,4,FALSE) -> 4 | I2: =LOWER(VLOOKUP($A2,'Judge Calibration'!$A:$E,5,FALSE))="yes" -> TRUE | J2: =I2=C2 -> FALSE | K2: =ABS(B2-H2)<=1 -> TRUE | M2: Items | N2: 14
A3: J02 | B3: 2 | C3: FALSE | D3: Risk IDs R05 and R06 are incorrectly categorized and do not match the descriptions in the risk register. | E3: R05; R06 | F3: gpt-4o-mini-2024-07-18 | G3: 831 | H3: =VLOOKUP($A3,'Judge Calibration'!$A:$E,4,FALSE) -> 2 | I3: =LOWER(VLOOKUP($A3,'Judge Calibration'!$A:$E,5,FALSE))="yes" -> FALSE | J3: =I3=C3 -> TRUE | K3: =ABS(B3-H3)<=1 -> TRUE | M3: Pass/fail agreement | N3: =COUNTIF(J2:J15,TRUE)/COUNTA(A2:A15) -> 0.64285714
A4: J03 | B4: 5 | C4: TRUE | D4: All selected risks are present in the register and relevant to the AI Adoption Project. | F4: gpt-4o-mini-2024-07-18 | G4: 646 | H4: =VLOOKUP($A4,'Judge Calibration'!$A:$E,4,FALSE) -> 3 | I4: =LOWER(VLOOKUP($A4,'Judge Calibration'!$A:$E,5,FALSE))="yes" -> FALSE | J4: =I4=C4 -> FALSE | K4: =ABS(B4-H4)<=1 -> FALSE | M4: Within ±1 on score | N4: =COUNTIF(K2:K15,TRUE)/COUNTA(A2:A15) -> 0.71428571
A5: J04 | B5: 2 | C5: FALSE | D5: Risk ID R11 is unrelated to AI adoption and logistics as it pertains to supply chain disruption without a direct link to the project's focus. | E5: R11 | F5: gpt-4o-mini-2024-07-18 | G5: 835 | H5: =VLOOKUP($A5,'Judge Calibration'!$A:$E,4,FALSE) -> 2 | I5: =LOWER(VLOOKUP($A5,'Judge Calibration'!$A:$E,5,FALSE))="yes" -> FALSE | J5: =I5=C5 -> TRUE | K5: =ABS(B5-H5)<=1 -> TRUE | M5: False passes (judge pass, human fail) | N5: =COUNTIFS(C2:C15,TRUE,I2:I15,FALSE) -> 3
A6: J05 | B6: 5 | C6: TRUE | D6: All risks and mitigations are relevant to the project and included in the risk register. | F6: gpt-4o-mini-2024-07-18 | G6: 790 | H6: =VLOOKUP($A6,'Judge Calibration'!$A:$E,4,FALSE) -> 2 | I6: =LOWER(VLOOKUP($A6,'Judge Calibration'!$A:$E,5,FALSE))="yes" -> FALSE | J6: =I6=C6 -> FALSE | K6: =ABS(B6-H6)<=1 -> FALSE | M6: False fails (judge fail, human pass) | N6: =COUNTIFS(C2:C15,FALSE,I2:I15,TRUE) -> 2
A7: J06 | B7: 5 | C7: TRUE | D7: All risks and mitigations are relevant and found in the risk register. | F7: gpt-4o-mini-2024-07-18 | G7: 839 | H7: =VLOOKUP($A7,'Judge Calibration'!$A:$E,4,FALSE) -> 5 | I7: =LOWER(VLOOKUP($A7,'Judge Calibration'!$A:$E,5,FALSE))="yes" -> TRUE | J7: =I7=C7 -> TRUE | K7: =ABS(B7-H7)<=1 -> TRUE | M7: Cohen’s kappa | N7: =(N3-N10)/(1-N10) -> 0.25531915
A8: J07 | B8: 5 | C8: TRUE | D8: All risks and mitigations are relevant and directly aligned with the project and the risk register. | F8: gpt-4o-mini-2024-07-18 | G8: 830 | H8: =VLOOKUP($A8,'Judge Calibration'!$A:$E,4,FALSE) -> 2 | I8: =LOWER(VLOOKUP($A8,'Judge Calibration'!$A:$E,5,FALSE))="yes" -> FALSE | J8: =I8=C8 -> FALSE | K8: =ABS(B8-H8)<=1 -> FALSE | M8: Human pass rate | N8: =COUNTIF(I2:I15,TRUE)/COUNTA(A2:A15) -> 0.35714286
A9: J08 | B9: 2 | C9: FALSE | D9: The mitigations provided do not fit the respective risks and are unrelated to the project. | E9: R01; R03; R09 | F9: gpt-4o-mini-2024-07-18 | G9: 809 | H9: =VLOOKUP($A9,'Judge Calibration'!$A:$E,4,FALSE) -> 2 | I9: =LOWER(VLOOKUP($A9,'Judge Calibration'!$A:$E,5,FALSE))="yes" -> FALSE | J9: =I9=C9 -> TRUE | K9: =ABS(B9-H9)<=1 -> TRUE | M9: Judge pass rate | N9: =COUNTIF(C2:C15,TRUE)/COUNTA(A2:A15) -> 0.42857143
A10: J09 | B10: 3 | C10: FALSE | D10: R04 is mentioned as implied but not explicitly listed in the register, leading to a lack of clear relevance. | E10: R04 | F10: gpt-4o-mini-2024-07-18 | G10: 825 | H10: =VLOOKUP($A10,'Judge Calibration'!$A:$E,4,FALSE) -> 3 | I10: =LOWER(VLOOKUP($A10,'Judge Calibration'!$A:$E,5,FALSE))="yes" -> FALSE | J10: =I10=C10 -> TRUE | K10: =ABS(B10-H10)<=1 -> TRUE | M10: Chance agreement | N10: =N8*N9+(1-N8)*(1-N9) -> 0.52040816
A11: J10 | B11: 5 | C11: TRUE | D11: All risks and mitigations are relevant and specific to the AI Adoption Project. | F11: gpt-4o-mini-2024-07-18 | G11: 844 | H11: =VLOOKUP($A11,'Judge Calibration'!$A:$E,4,FALSE) -> 5 | I11: =LOWER(VLOOKUP($A11,'Judge Calibration'!$A:$E,5,FALSE))="yes" -> TRUE | J11: =I11=C11 -> TRUE | K11: =ABS(B11-H11)<=1 -> TRUE
A12: J11 | B12: 2 | C12: FALSE | D12: The risk of driver shortage is unrelated to AI adoption and logistics as per the reference risk register. | E12: Driver shortage in the delivery fleet | F12: gpt-4o-mini-2024-07-18 | G12: 842 | H12: =VLOOKUP($A12,'Judge Calibration'!$A:$E,4,FALSE) -> 2 | I12: =LOWER(VLOOKUP($A12,'Judge Calibration'!$A:$E,5,FALSE))="yes" -> FALSE | J12: =I12=C12 -> TRUE | K12: =ABS(B12-H12)<=1 -> TRUE
A13: J12 | B13: 2 | C13: FALSE | D13: All identified risks are unrelated to the AI adoption project and logistics. | E13: Office relocation; Staff holiday clashes; Printer budget overrun | F13: gpt-4o-mini-2024-07-18 | G13: 766 | H13: =VLOOKUP($A13,'Judge Calibration'!$A:$E,4,FALSE) -> 1 | I13: =LOWER(VLOOKUP($A13,'Judge Calibration'!$A:$E,5,FALSE))="yes" -> FALSE | J13: =I13=C13 -> TRUE | K13: =ABS(B13-H13)<=1 -> TRUE
A14: J13 | B14: 2 | C14: FALSE | D14: The risks mentioned are relevant, but the tasks referenced are not part of the risk register and do not relate to logistics or AI adoption. | E14: T024; T025; T006 | F14: gpt-4o-mini-2024-07-18 | G14: 784 | H14: =VLOOKUP($A14,'Judge Calibration'!$A:$E,4,FALSE) -> 4 | I14: =LOWER(VLOOKUP($A14,'Judge Calibration'!$A:$E,5,FALSE))="yes" -> TRUE | J14: =I14=C14 -> FALSE | K14: =ABS(B14-H14)<=1 -> FALSE
A15: J14 | B15: 5 | C15: TRUE | D15: All risks and mitigations are relevant and directly aligned with the project and the risk register. | F15: gpt-4o-mini-2024-07-18 | G15: 843 | H15: =VLOOKUP($A15,'Judge Calibration'!$A:$E,4,FALSE) -> 5 | I15: =LOWER(VLOOKUP($A15,'Judge Calibration'!$A:$E,5,FALSE))="yes" -> TRUE | J15: =I15=C15 -> TRUE | K15: =ABS(B15-H15)<=1 -> TRUE

Sheet Test Set
A1: id | B1: request | C1: answer | D1: human_score_1to5 | E1: human_pass_yes_no | F1: human_notes | H1: Note: Combined test set: 19 items (K01 to K13 plus L01 to L06). Rated blind by a human; used to compare judge v1 and v2. Replaces the former Held-out and heldout_extra_BLIND tabs
A2: K01 | B2: Generate a risk assessment for the AI Adoption Project at ABCDE Ltd. | C2: ### Top Risks and Why 1. **R06 - Cost Overruns**: The task T009 (Vendor evaluation for ML platform) is still To Do, so platform costs are not yet known. 2. **R02 - Integration Issues**: The task T005 (Map current logistics workflows) is Done and shows several legacy systems that will need connectors. 3. **R08 - Model Performance Drift**: The task T010 (Collect historical demand data) is still To Do, so there is no baseline to monitor drift against. 4. **R05 - Ethical & Legal Concerns**: The task T025 (Legal review of data usage) is In Progress, so legal risks are still open. | D2: 3 | E2: no | F2: reasons for R02 and R08 are not in line with the ground truth data
A3: K02 | B3: What are the top 3 risks for the ABCDE Ltd project based on the risk data? | C3: 1. **Risk ID:** R02 **Category:** Integration Issues **Impact:** Delays in deployment and operational disruptions **Mitigation:** Plan integration roadmap and use APIs/middleware **Reason:** The task T027 (API gateway rollout) is delayed, which threatens integration. 2. **Risk ID:** R09 **Category:** Security Vulnerabilities **Impact:** Data breaches and operational risks **Mitigation:** Adopt AI security best practices and penetration testing **Reason:** The task T028 (Penetration test) is overdue, so security gaps may remain. 3. **Risk ID:** R07 **Category:** Unrealistic Expectations **Impact:** Disillusionment and loss of support **Mitigation:** Align expectations and show quick wins **Reason:** The task T040 (Stakeholder expectations workshop) was cancelled, which may inflate expectations. | D3: 2 | E3: no | F3: referencing tasks that are not listed in the groundtruth
A4: K03 | B4: What are the top 3 risks for the ABCDE Ltd project based on the risk data? | C4: 1. **Risk ID:** R02 **Category:** Integration Issues **Impact:** Delays in deployment and operational disruptions **Mitigation:** Plan integration roadmap and use APIs/middleware **Reason:** The task T005 (Map current logistics workflows) is Done and exposed the legacy systems the new tools must connect to, so integration effort is now visible. 2. **Risk ID:** R09 **Category:** Security Vulnerabilities **Impact:** Data breaches and operational risks **Mitigation:** Adopt AI security best practices and penetration testing **Reason:** The task T024 (Security review of AI infrastructure) is Blocked waiting on the security team, so security risks remain unreviewed. 3. **Risk ID:** R07 **Category:** Unrealistic Expectations **Impact:** Disillusionment and loss of support **Mitigation:** Align expectations and show quick wins **Reason:** The task T008 (Define success criteria for each use case) is flagged At risk, so expectations may be set before success is defined. | D4: 2 | E4: no | F4: reason for R02 does not categorized it as being a top reason
A5: K04 | B5: What are the top 3 risks for the ABCDE Ltd project based on the risk data? | C5: 1. **Risk ID:** R03 **Category:** Talent & Skills Gap **Impact:** Overreliance on external vendors and slow progress **Mitigation:** Provide staff training and hire specialized talent **Reason:** The task T007 (Shortlist AI use cases) is In Progress and needs skills the team may lack. 2. **Risk ID:** R08 **Category:** Model Performance Drift **Impact:** Incorrect decisions and trust erosion **Mitigation:** Regular retraining cycles and monitoring dashboards **Reason:** The task T010 (Collect historical demand data) is still To Do, so drift cannot yet be monitored. 3. **Risk ID:** R12 **Category:** Regulatory Change **Impact:** New rules could force redesign **Mitigation:** Track regulatory updates monthly **Reason:** Customs rules may change during the pilot. | D5: 2 | E5: no | F5: R12 is not in the list, hallicullation
A6: K05 | B6: What are the top 3 risks for the ABCDE Ltd project based on the risk data? | C6: 1. **Risk ID:** R08 **Category:** Security Vulnerabilities **Impact:** Incorrect decisions and trust erosion **Mitigation:** Regular retraining cycles and monitoring dashboards **Reason:** The task T010 (Collect historical demand data) is still To Do. 2. **Risk ID:** R09 **Category:** Model Performance Drift **Impact:** Data breaches and operational risks **Mitigation:** Adopt AI security best practices and penetration testing **Reason:** The task T024 (Security review of AI infrastructure) is Blocked. 3. **Risk ID:** R03 **Category:** Talent & Skills Gap **Impact:** Overreliance on external vendors and slow progress **Mitigation:** Provide staff training and hire specialized talent **Reason:** The task T007 (Shortlist AI use cases) is In Progress and needs scarce skills. | D6: 2 | E6: no | F6: wrong risk ID for R08 and R09
A7: K06 | B7: What are the top 3 risks for the ABCDE Ltd project based on the risk data? | C7: 1. **Risk ID:** R08 **Category:** Model Performance Drift **Impact:** Incorrect decisions and trust erosion **Mitigation:** Regular retraining cycles and monitoring dashboards **Reason:** This is a common risk in technology projects. 2. **Risk ID:** R03 **Category:** Talent & Skills Gap **Impact:** Overreliance on external vendors and slow progress **Mitigation:** Provide staff training and hire specialized talent **Reason:** Many organisations struggle to find skilled people. 3. **Risk ID:** R10 **Category:** Vendor Lock-in **Impact:** Flexibility loss and future switching costs **Mitigation:** Favor open standards and negotiate flexible vendor terms **Reason:** Being tied to one supplier is generally risky. | D7: 2 | E7: no | F7: reasons not generally in consistent to groundtruth data
A8: K07 | B8: What are the top 3 risks for the ABCDE Ltd project based on the risk data? | C8: 1. **Risk ID:** R01 **Category:** Data Quality & Availability **Impact:** Poor model performance and inaccurate outcomes **Mitigation:** Perform early data audits and implement robust data governance **Reason:** The task T006 (Identify data gaps and quality issues) is In Progress, so the quality of the training data is not yet confirmed. 2. **Risk ID:** R10 **Category:** Vendor Lock-in **Impact:** Flexibility loss and future switching costs **Mitigation:** Favor open standards and negotiate flexible vendor terms **Reason:** The task T009 (Vendor evaluation for ML platform) is still To Do, so dependence on one platform has not been assessed. 3. **Risk ID:** R05 **Category:** Ethical & Legal Concerns **Impact:** Legal repercussions and reputational damage **Mitigation:** Involve legal early and implement fairness checks **Reason:** The task T025 (Legal review of data usage) is In Progress, so legal clearance for the data is still open. | D8: 5 | E8: yes | F8: answers is correct and in line with groundtruth data
A9: K08 | B9: What are the top 3 risks for the ABCDE Ltd project based on the risk data? | C9: The top three risks are R02 Integration Issues, R08 Model Performance Drift and R09 Security Vulnerabilities. | D9: 2 | E9: no | F9: no reasons and details
A10: K09 | B10: What are the top 3 risks for the ABCDE Ltd project based on the risk data? | C10: 1. **Risk ID:** R01 **Category:** Data Quality & Availability **Impact:** Poor model performance and inaccurate outcomes **Mitigation:** Perform early data audits and implement robust data governance **Reason:** The task T006 (Identify data gaps and quality issues) is In Progress. 2. **Risk ID:** R02 **Category:** Integration Issues **Impact:** Delays in deployment and operational disruptions **Mitigation:** Plan integration roadmap and use APIs/middleware **Reason:** The task T005 (Map current logistics workflows) is Done and shows legacy dependencies. 3. **Risk:** Fleet telematics outage **Impact:** Loss of live vehicle data during the pilot **Mitigation:** Add an offline data capture fallback **Reason:** Route models depend on live telematics feeds. | D10: 2 | E10: no | F10: hallicullation, manfautured data
A11: K10 | B11: What are the top 3 risks for the ABCDE Ltd project based on the risk data? | C11: 1. **Risk ID:** R09 **Category:** Security Vulnerabilities **Impact:** Data breaches and operational risks **Mitigation:** Adopt AI security best practices and penetration testing **Reason:** The task T008 (Define success criteria for each use case) is flagged At risk. 2. **Risk ID:** R01 **Category:** Data Quality & Availability **Impact:** Poor model performance and inaccurate outcomes **Mitigation:** Perform early data audits and implement robust data governance **Reason:** The task T009 (Vendor evaluation for ML platform) is still To Do. 3. **Risk ID:** R06 **Category:** Cost Overruns **Impact:** Budget constraints and project delays **Mitigation:** Set realistic budget and build in contingency funds **Reason:** The task T004 (Audit existing data infrastructure) is Done. | D11: 3 | E11: no | F11: based on the reason, it should be not flagged as a risk
A12: K11 | B12: What are the top 3 risks for the ABCDE Ltd project based on the risk data? | C12: 1. **Risk ID:** R04 **Category:** Change Resistance **Impact:** Low adoption and reduced ROI **Mitigation:** Strong change management and early engagement **Reason:** The task T007 (Shortlist AI use cases) is In Progress, and the shortlisted use cases will change how staff work, so early engagement matters. 2. **Risk ID:** R07 **Category:** Unrealistic Expectations **Impact:** Disillusionment and loss of support **Mitigation:** Align expectations and show quick wins **Reason:** The task T008 (Define success criteria for each use case) is flagged At risk, so targets may be promised before they are defined. 3. **Risk ID:** R05 **Category:** Ethical & Legal Concerns **Impact:** Legal repercussions and reputational damage **Mitigation:** Involve legal early and implement fairness checks **Reason:** The task T025 (Legal review of data usage) is In Progress, so privacy obligations are not yet confirmed. | D12: 5 | E12: yes | F12: answered correctly, in line with ground truth
A13: K12 | B13: What are the top 3 risks for the ABCDE Ltd project based on the risk data? | C13: 1. **Risk ID:** R05 **Category:** Ethical & Legal Concerns **Impact:** Legal repercussions and reputational damage **Mitigation:** Order extra laptops for the team **Reason:** The task T025 (Legal review of data usage) is In Progress. 2. **Risk ID:** R08 **Category:** Model Performance Drift **Impact:** Incorrect decisions and trust erosion **Mitigation:** Hold a team-building day **Reason:** The task T010 (Collect historical demand data) is still To Do. 3. **Risk ID:** R02 **Category:** Integration Issues **Impact:** Delays in deployment and operational disruptions **Mitigation:** Extend the lunch break **Reason:** The task T005 (Map current logistics workflows) is Done. | D13: 2 | E13: no | F13: mitigation, not in line with ground truth
... A20: L06 | B20: What are the top 3 risks for the ABCDE Ltd project based on the risk data? | C20: 1. **Risk ID:** R04 **Category:** Change Resistance **Impact:** Low adoption and reduced ROI **Mitigation:** Strong change management and early engagement **Reason:** The task T033 (Change champion programme) is overdue. 2. **Risk ID:** R06 **Category:** Cost Overruns **Impact:** Budget constraints and project delays **Mitigation:** Set realistic budget and build in contingency funds **Reason:** The task T034 (Budget approval) is Blocked. 3. **Risk ID:** R02 **Category:** Integration Issues **Impact:** Delays in deployment and operational disruptions **Mitigation:** Plan integration roadmap and use APIs/middleware **Reason:** The task T035 (Systems integration test) has not started. | D20: 2 | E20: no | F20: manfactured data

Sheet Test Results
A1: id | B1: judge_version | C1: judge_score | D1: judge_pass | E1: judge_reason | F1: unsupported | G1: judgeModel | H1: judgeTokens | I1: human_score | J1: human_pass | K1: agree | M1: Measure | N1: V1 | O1: V2
A2: K01 | B2: v1 | C2: 5 | D2: TRUE | E2: All risks mentioned are in the register and relevant to the AI Adoption Project. | G2: gpt-4o-mini-2024-07-18 | H2: 774 | I2: =VLOOKUP($A2,'Test Set'!$A:$E,4,FALSE) -> 3 | J2: =LOWER(VLOOKUP($A2,'Test Set'!$A:$E,5,FALSE))="yes" -> FALSE | K2: =J2=D2 -> FALSE | M2: Items | N2: =COUNTIFS($B$2:$B$39,"v1") -> 19 | O2: =COUNTIFS($B$2:$B$39,"v2") -> 19
A3: K01 | B3: v2 | C3: 4 | D3: TRUE | E3: The risks identified are relevant to the project, but the mention of tasks without specific mitigations for each risk leads to minor generic wording. | G3: gpt-4o-mini-2024-07-18 | H3: 922 | I3: =VLOOKUP($A3,'Test Set'!$A:$E,4,FALSE) -> 3 | J3: =LOWER(VLOOKUP($A3,'Test Set'!$A:$E,5,FALSE))="yes" -> FALSE | K3: =J3=D3 -> FALSE | M3: Agreement | N3: =COUNTIFS($B$2:$B$39,N$1,$K$2:$K$39,TRUE)/N2 -> 0.57894737 | O3: =COUNTIFS($B$2:$B$39,"v2",$K$2:$K$39,TRUE)/O2 -> 0.68421053
A4: K02 | B4: v1 | C4: 5 | D4: TRUE | E4: All risks and mitigations are relevant and directly aligned with the project and the risk register. | G4: gpt-4o-mini-2024-07-18 | H4: 823 | I4: =VLOOKUP($A4,'Test Set'!$A:$E,4,FALSE) -> 2 | J4: =LOWER(VLOOKUP($A4,'Test Set'!$A:$E,5,FALSE))="yes" -> FALSE | K4: =J4=D4 -> FALSE | M4: False passes | N4: =COUNTIFS($B$2:$B$39,N$1,$D$2:$D$39,TRUE,$J$2:$J$39,FALSE) -> 7 | O4: =COUNTIFS($B$2:$B$39,"v2",$D$2:$D$39,TRUE,$J$2:$J$39,FALSE) -> 3
A5: K02 | B5: v2 | C5: 2 | D5: FALSE | E5: The cited task IDs are beyond the project board's range, making the risks unsupported. | F5: T027; T028; T040 | G5: gpt-4o-mini-2024-07-18 | H5: 971 | I5: =VLOOKUP($A5,'Test Set'!$A:$E,4,FALSE) -> 2 | J5: =LOWER(VLOOKUP($A5,'Test Set'!$A:$E,5,FALSE))="yes" -> FALSE | K5: =J5=D5 -> TRUE | M5: False fails | N5: =COUNTIFS($B$2:$B$39,"v1",$D$2:$D$39,FALSE,$J$2:$J$39,TRUE) -> 1 | O5: =COUNTIFS($B$2:$B$39,"v2",$D$2:$D$39,FALSE,$J$2:$J$39,TRUE) -> 3
A6: K03 | B6: v1 | C6: 5 | D6: TRUE | E6: All risks and mitigations are relevant to the AI Adoption Project and logistics. | G6: gpt-4o-mini-2024-07-18 | H6: 854 | I6: =VLOOKUP($A6,'Test Set'!$A:$E,4,FALSE) -> 2 | J6: =LOWER(VLOOKUP($A6,'Test Set'!$A:$E,5,FALSE))="yes" -> FALSE | K6: =J6=D6 -> FALSE | M6: Human pass rate | N6: =COUNTIFS($B$2:$B$39,"v1",$J$2:$J$39,TRUE)/N2 -> 0.31578947 | O6: =COUNTIFS($B$2:$B$39,"v2",$J$2:$J$39,TRUE)/O2 -> 0.31578947
A7: K03 | B7: v2 | C7: 2 | D7: FALSE | E7: The inclusion of task T024, which is above the valid range, leads to a score of 2. | F7: T024 | G7: gpt-4o-mini-2024-07-18 | H7: 1004 | I7: =VLOOKUP($A7,'Test Set'!$A:$E,4,FALSE) -> 2 | J7: =LOWER(VLOOKUP($A7,'Test Set'!$A:$E,5,FALSE))="yes" -> FALSE | K7: =J7=D7 -> TRUE | M7: Judge pass rate | N7: =COUNTIFS($B$2:$B$39,"v1",$D$2:$D$39,TRUE)/N2 -> 0.63157895 | O7: =COUNTIFS($B$2:$B$39,"v2",$D$2:$D$39,TRUE)/O2 -> 0.31578947
A8: K04 | B8: v1 | C8: 2 | D8: FALSE | E8: Risk ID R12 is not in the register and is unrelated to logistics or AI adoption. | F8: R12 | G8: gpt-4o-mini-2024-07-18 | H8: 823 | I8: =VLOOKUP($A8,'Test Set'!$A:$E,4,FALSE) -> 2 | J8: =LOWER(VLOOKUP($A8,'Test Set'!$A:$E,5,FALSE))="yes" -> FALSE | K8: =J8=D8 -> TRUE | M8: Chance agreement | N8: =N6*N7+(1-N6)*(1-N7) -> 0.45152355 | O8: =O6*O7+(1-O6)*(1-O7) -> 0.56786704
A9: K04 | B9: v2 | C9: 2 | D9: FALSE | E9: Risk R12 is not in the reference risk register and is unrelated to the project. | F9: R12 | G9: gpt-4o-mini-2024-07-18 | H9: 962 | I9: =VLOOKUP($A9,'Test Set'!$A:$E,4,FALSE) -> 2 | J9: =LOWER(VLOOKUP($A9,'Test Set'!$A:$E,5,FALSE))="yes" -> FALSE | K9: =J9=D9 -> TRUE | M9: Cohen’s kappa | N9: =(N3-N8)/(1-N8) -> 0.23232323 | O9: =(O3-O8)/(1-O8) -> 0.26923077
A10: K05 | B10: v1 | C10: 2 | D10: FALSE | E10: Risks R08 and R09 are incorrectly categorized and do not match the descriptions in the risk register. | F10: R08; R09 | G10: gpt-4o-mini-2024-07-18 | H10: 831 | I10: =VLOOKUP($A10,'Test Set'!$A:$E,4,FALSE) -> 2 | J10: =LOWER(VLOOKUP($A10,'Test Set'!$A:$E,5,FALSE))="yes" -> FALSE | K10: =J10=D10 -> TRUE
A11: K05 | B11: v2 | C11: 2 | D11: FALSE | E11: Risk R09 is incorrectly categorized, and tasks T010 and T024 are not valid risks. | F11: R09; T010; T024 | G11: gpt-4o-mini-2024-07-18 | H11: 988 | I11: =VLOOKUP($A11,'Test Set'!$A:$E,4,FALSE) -> 2 | J11: =LOWER(VLOOKUP($A11,'Test Set'!$A:$E,5,FALSE))="yes" -> FALSE | K11: =J11=D11 -> TRUE
A12: K06 | B12: v1 | C12: 5 | D12: TRUE | E12: All risks and mitigations are relevant and specific to the AI Adoption Project. | G12: gpt-4o-mini-2024-07-18 | H12: 798 | I12: =VLOOKUP($A12,'Test Set'!$A:$E,4,FALSE) -> 2 | J12: =LOWER(VLOOKUP($A12,'Test Set'!$A:$E,5,FALSE))="yes" -> FALSE | K12: =J12=D12 -> FALSE
A13: K06 | B13: v2 | C13: 3 | D13: FALSE | E13: The risks are relevant, but the reasons provided are generic and not specific to this project's context. | G13: gpt-4o-mini-2024-07-18 | H13: 942 | I13: =VLOOKUP($A13,'Test Set'!$A:$E,4,FALSE) -> 2 | J13: =LOWER(VLOOKUP($A13,'Test Set'!$A:$E,5,FALSE))="yes" -> FALSE | K13: =J13=D13 -> TRUE
A14: K07 | B14: v1 | C14: 3 | D14: FALSE | E14: Risk ID R10 is not in the reference risk register. | F14: R10 | G14: gpt-4o-mini-2024-07-18 | H14: 853 | I14: =VLOOKUP($A14,'Test Set'!$A:$E,4,FALSE) -> 5 | J14: =LOWER(VLOOKUP($A14,'Test Set'!$A:$E,5,FALSE))="yes" -> TRUE | K14: =J14=D14 -> FALSE
A15: K07 | B15: v2 | C15: 2 | D15: FALSE | E15: Task IDs T006 and T009 are not within the valid range of project board tasks, which limits the relevance of the risks presented. | F15: T006; T009 | G15: gpt-4o-mini-2024-07-18 | H15: 1011 | I15: =VLOOKUP($A15,'Test Set'!$A:$E,4,FALSE) -> 5 | J15: =LOWER(VLOOKUP($A15,'Test Set'!$A:$E,5,FALSE))="yes" -> TRUE | K15: =J15=D15 -> FALSE
A16: K08 | B16: v1 | C16: 5 | D16: TRUE | E16: All identified risks are present in the register and relevant to the AI Adoption Project. | G16: gpt-4o-mini-2024-07-18 | H16: 658 | I16: =VLOOKUP($A16,'Test Set'!$A:$E,4,FALSE) -> 2 | J16: =LOWER(VLOOKUP($A16,'Test Set'!$A:$E,5,FALSE))="yes" -> FALSE | K16: =J16=D16 -> FALSE
A17: K08 | B17: v2 | C17: 5 | D17: TRUE | E17: All listed risks are present in the register and relevant to the AI Adoption Project. | G17: gpt-4o-mini-2024-07-18 | H17: 794 | I17: =VLOOKUP($A17,'Test Set'!$A:$E,4,FALSE) -> 2 | J17: =LOWER(VLOOKUP($A17,'Test Set'!$A:$E,5,FALSE))="yes" -> FALSE | K17: =J17=D17 -> FALSE
A18: K09 | B18: v1 | C18: 2 | D18: FALSE | E18: The risk of 'Fleet telematics outage' is not in the register and is unrelated to the project. | F18: Fleet telematics outage | G18: gpt-4o-mini-2024-07-18 | H18: 817 | I18: =VLOOKUP($A18,'Test Set'!$A:$E,4,FALSE) -> 2 | J18: =LOWER(VLOOKUP($A18,'Test Set'!$A:$E,5,FALSE))="yes" -> FALSE | K18: =J18=D18 -> TRUE
A19: K09 | B19: v2 | C19: 2 | D19: FALSE | E19: The risk 'Fleet telematics outage' is not in the register and is unrelated to the project. | F19: Fleet telematics outage | G19: gpt-4o-mini-2024-07-18 | H19: 956 | I19: =VLOOKUP($A19,'Test Set'!$A:$E,4,FALSE) -> 2 | J19: =LOWER(VLOOKUP($A19,'Test Set'!$A:$E,5,FALSE))="yes" -> FALSE | K19: =J19=D19 -> TRUE
A20: K10 | B20: v1 | C20: 5 | D20: TRUE | E20: All risks and mitigations are relevant and present in the risk register. | G20: gpt-4o-mini-2024-07-18 | H20: 815 | I20: =VLOOKUP($A20,'Test Set'!$A:$E,4,FALSE) -> 3 | J20: =LOWER(VLOOKUP($A20,'Test Set'!$A:$E,5,FALSE))="yes" -> FALSE | K20: =J20=D20 -> FALSE
A21: K10 | B21: v2 | C21: 5 | D21: TRUE | E21: All listed risks and mitigations are relevant to the project and match the reference risk register. | G21: gpt-4o-mini-2024-07-18 | H21: 959 | I21: =VLOOKUP($A21,'Test Set'!$A:$E,4,FALSE) -> 3 | J21: =LOWER(VLOOKUP($A21,'Test Set'!$A:$E,5,FALSE))="yes" -> FALSE | K21: =J21=D21 -> FALSE
A22: K11 | B22: v1 | C22: 5 | D22: TRUE | E22: All risks and mitigations are relevant to the project and align with the risk register. | G22: gpt-4o-mini-2024-07-18 | H22: 850 | I22: =VLOOKUP($A22,'Test Set'!$A:$E,4,FALSE) -> 5 | J22: =LOWER(VLOOKUP($A22,'Test Set'!$A:$E,5,FALSE))="yes" -> TRUE | K22: =J22=D22 -> TRUE
A23: K11 | B23: v2 | C23: 5 | D23: TRUE | E23: All risks and mitigations are relevant to the project and align with the risk register. | G23: gpt-4o-mini-2024-07-18 | H23: 990 | I23: =VLOOKUP($A23,'Test Set'!$A:$E,4,FALSE) -> 5 | J23: =LOWER(VLOOKUP($A23,'Test Set'!$A:$E,5,FALSE))="yes" -> TRUE | K23: =J23=D23 -> TRUE
A24: K12 | B24: v1 | C24: 2 | D24: FALSE | E24: The mitigations provided do not fit the respective risks and are unrelated to the project. | F24: R05; R08; R02 | G24: gpt-4o-mini-2024-07-18 | H24: 815 | I24: =VLOOKUP($A24,'Test Set'!$A:$E,4,FALSE) -> 2 | J24: =LOWER(VLOOKUP($A24,'Test Set'!$A:$E,5,FALSE))="yes" -> FALSE | K24: =J24=D24 -> TRUE
A25: K12 | B25: v2 | C25: 2 | D25: FALSE | E25: The mitigations provided do not fit the respective risks and the cited tasks are beyond the valid range. | F25: T025; T010; T005 | G25: gpt-4o-mini-2024-07-18 | H25: 958 | I25: =VLOOKUP($A25,'Test Set'!$A:$E,4,FALSE) -> 2 | J25: =LOWER(VLOOKUP($A25,'Test Set'!$A:$E,5,FALSE))="yes" -> FALSE | K25: =J25=D25 -> TRUE
A26: K13 | B26: v1 | C26: 2 | D26: FALSE | E26: All listed risks are unrelated to logistics or AI adoption and do not appear in the risk register. | F26: Cafeteria menu change; Parking permit shortage; Brand colour refresh | G26: gpt-4o-mini-2024-07-18 | H26: 767 | I26: =VLOOKUP($A26,'Test Set'!$A:$E,4,FALSE) -> 1 | J26: =LOWER(VLOOKUP($A26,'Test Set'!$A:$E,5,FALSE))="yes" -> FALSE | K26: =J26=D26 -> TRUE
A27: K13 | B27: v2 | C27: 2 | D27: FALSE | E27: The listed risks are unrelated to the AI Adoption Project and do not appear in the risk register. | F27: Cafeteria menu change; Parking permit shortage; Brand colour refresh | G27: gpt-4o-mini-2024-07-18 | H27: 907 | I27: =VLOOKUP($A27,'Test Set'!$A:$E,4,FALSE) -> 1 | J27: =LOWER(VLOOKUP($A27,'Test Set'!$A:$E,5,FALSE))="yes" -> FALSE | K27: =J27=D27 -> TRUE
A28: L01 | B28: v1 | C28: 5 | D28: TRUE | E28: All risks and mitigations are relevant and directly aligned with the AI Adoption Project. | G28: gpt-4o-mini-2024-07-18 | H28: 841 | I28: =VLOOKUP($A28,'Test Set'!$A:$E,4,FALSE) -> 5 | J28: =LOWER(VLOOKUP($A28,'Test Set'!$A:$E,5,FALSE))="yes" -> TRUE | K28: =J28=D28 -> TRUE
A29: L01 | B29: v2 | C29: 5 | D29: TRUE | E29: All risks and mitigations are relevant to the project and the register. | G29: gpt-4o-mini-2024-07-18 | H29: 979 | I29: =VLOOKUP($A29,'Test Set'!$A:$E,4,FALSE) -> 5 | J29: =LOWER(VLOOKUP($A29,'Test Set'!$A:$E,5,FALSE))="yes" -> TRUE | K29: =J29=D29 -> TRUE
A30: L02 | B30: v1 | C30: 5 | D30: TRUE | E30: All risks and mitigations are relevant and directly aligned with the project and the risk register. | G30: gpt-4o-mini-2024-07-18 | H30: 845 | I30: =VLOOKUP($A30,'Test Set'!$A:$E,4,FALSE) -> 5 | J30: =LOWER(VLOOKUP($A30,'Test Set'!$A:$E,5,FALSE))="yes" -> TRUE | K30: =J30=D30 -> TRUE
A31: L02 | B31: v2 | C31: 5 | D31: TRUE | E31: All risks and mitigations are relevant to the project and the register. | G31: gpt-4o-mini-2024-07-18 | H31: 981 | I31: =VLOOKUP($A31,'Test Set'!$A:$E,4,FALSE) -> 5 | J31: =LOWER(VLOOKUP($A31,'Test Set'!$A:$E,5,FALSE))="yes" -> TRUE | K31: =J31=D31 -> TRUE
A32: L03 | B32: v1 | C32: 5 | D32: TRUE | E32: All risks and mitigations are relevant and directly aligned with the AI Adoption Project and the reference risk register. | G32: gpt-4o-mini-2024-07-18 | H32: 826 | I32: =VLOOKUP($A32,'Test Set'!$A:$E,4,FALSE) -> 5 | J32: =LOWER(VLOOKUP($A32,'Test Set'!$A:$E,5,FALSE))="yes" -> TRUE | K32: =J32=D32 -> TRUE
A33: L03 | B33: v2 | C33: 2 | D33: FALSE | E33: The cited task IDs are beyond the valid range and unrelated to the risks presented. | F33: T009; T010 | G33: gpt-4o-mini-2024-07-18 | H33: 967 | I33: =VLOOKUP($A33,'Test Set'!$A:$E,4,FALSE) -> 5 | J33: =LOWER(VLOOKUP($A33,'Test Set'!$A:$E,5,FALSE))="yes" -> TRUE | K33: =J33=D33 -> FALSE
A34: L04 | B34: v1 | C34: 2 | D34: FALSE | E34: Risk ID R13 is unrelated to logistics or AI adoption and does not appear in the risk register. | F34: R13 | G34: gpt-4o-mini-2024-07-18 | H34: 822 | I34: =VLOOKUP($A34,'Test Set'!$A:$E,4,FALSE) -> 2 | J34: =LOWER(VLOOKUP($A34,'Test Set'!$A:$E,5,FALSE))="yes" -> FALSE | K34: =J34=D34 -> TRUE
A35: L04 | B35: v2 | C35: 2 | D35: FALSE | E35: Risk R13 is unrelated to the project, and task T006 is not within the valid task range. | F35: R13; T006 | G35: gpt-4o-mini-2024-07-18 | H35: 966 | I35: =VLOOKUP($A35,'Test Set'!$A:$E,4,FALSE) -> 2 | J35: =LOWER(VLOOKUP($A35,'Test Set'!$A:$E,5,FALSE))="yes" -> FALSE | K35: =J35=D35 -> TRUE
A36: L05 | B36: v1 | C36: 5 | D36: TRUE | E36: All risks listed are in the register and relevant to the AI Adoption Project. | G36: gpt-4o-mini-2024-07-18 | H36: 726 | I36: =VLOOKUP($A36,'Test Set'!$A:$E,4,FALSE) -> 5 | J36: =LOWER(VLOOKUP($A36,'Test Set'!$A:$E,5,FALSE))="yes" -> TRUE | K36: =J36=D36 -> TRUE
A37: L05 | B37: v2 | C37: 2 | D37: FALSE | E37: The cited task IDs are beyond the valid range and not risks in the register. | F37: T024; T025; T009 | G37: gpt-4o-mini-2024-07-18 | H37: 872 | I37: =VLOOKUP($A37,'Test Set'!$A:$E,4,FALSE) -> 5 | J37: =LOWER(VLOOKUP($A37,'Test Set'!$A:$E,5,FALSE))="yes" -> TRUE | K37: =J37=D37 -> FALSE
A38: L06 | B38: v1 | C38: 5 | D38: TRUE | E38: All risks and mitigations are relevant and directly aligned with the project and risk register. | G38: gpt-4o-mini-2024-07-18 | H38: 803 | I38: =VLOOKUP($A38,'Test Set'!$A:$E,4,FALSE) -> 2 | J38: =LOWER(VLOOKUP($A38,'Test Set'!$A:$E,5,FALSE))="yes" -> FALSE | K38: =J38=D38 -> FALSE
A39: L06 | B39: v2 | C39: 2 | D39: FALSE | E39: The cited task IDs are beyond the allowed range and not relevant to the risks presented. | F39: T033; T034; T035 | G39: gpt-4o-mini-2024-07-18 | H39: 952 | I39: =VLOOKUP($A39,'Test Set'!$A:$E,4,FALSE) -> 2 | J39: =LOWER(VLOOKUP($A39,'Test Set'!$A:$E,5,FALSE))="yes" -> FALSE | K39: =J39=D39 -> TRUE
